{
"meta":{"test_sets":[],"test_metrics":[],"learn_metrics":[{"best_value":"Min","name":"RMSE"}],"launch_mode":"Train","parameters":"","iteration_count":1000,"learn_sets":["learn"],"name":"experiment"},
"iterations":[
{"learn":[86.48700875],"iteration":0,"passed_time":0.002682871835,"remaining_time":2.680188963},
{"learn":[83.28030507],"iteration":1,"passed_time":0.005542685594,"remaining_time":2.765800111},
{"learn":[80.17213623],"iteration":2,"passed_time":0.008199764915,"remaining_time":2.725055207},
{"learn":[77.27955184],"iteration":3,"passed_time":0.01071501421,"remaining_time":2.668038539},
{"learn":[74.52965535],"iteration":4,"passed_time":0.01325922968,"remaining_time":2.638586707},
{"learn":[71.95292458],"iteration":5,"passed_time":0.01591849305,"remaining_time":2.637163682},
{"learn":[69.5209592],"iteration":6,"passed_time":0.03632839635,"remaining_time":5.153442511},
{"learn":[67.35500722],"iteration":7,"passed_time":0.04777397231,"remaining_time":5.923972567},
{"learn":[65.2761313],"iteration":8,"passed_time":0.05044823838,"remaining_time":5.554911581},
{"learn":[63.35254388],"iteration":9,"passed_time":0.05301685274,"remaining_time":5.248668421},
{"learn":[61.52898664],"iteration":10,"passed_time":0.05555520969,"remaining_time":4.994918399},
{"learn":[59.87615286],"iteration":11,"passed_time":0.05801774914,"remaining_time":4.776794679},
{"learn":[58.36114208],"iteration":12,"passed_time":0.06061391765,"remaining_time":4.601995132},
{"learn":[57.06540713],"iteration":13,"passed_time":0.06325643588,"remaining_time":4.455060413},
{"learn":[55.73925833],"iteration":14,"passed_time":0.06582492704,"remaining_time":4.322503542},
{"learn":[54.46014215],"iteration":15,"passed_time":0.06846683165,"remaining_time":4.210710147},
{"learn":[53.27153141],"iteration":16,"passed_time":0.07098804347,"remaining_time":4.104779219},
{"learn":[52.15336894],"iteration":17,"passed_time":0.07353150773,"remaining_time":4.011552255},
{"learn":[51.20413429],"iteration":18,"passed_time":0.07628926025,"remaining_time":3.938934964},
{"learn":[50.31740966],"iteration":19,"passed_time":0.07881358493,"remaining_time":3.861865662},
{"learn":[49.50195553],"iteration":20,"passed_time":0.08139938363,"remaining_time":3.794761742},
{"learn":[48.70503468],"iteration":21,"passed_time":0.08410210626,"remaining_time":3.738720906},
{"learn":[47.90974252],"iteration":22,"passed_time":0.08667004781,"remaining_time":3.6815929},
{"learn":[47.18156584],"iteration":23,"passed_time":0.08932990798,"remaining_time":3.632749591},
{"learn":[46.58053768],"iteration":24,"passed_time":0.09190483687,"remaining_time":3.584288638},
{"learn":[45.93923281],"iteration":25,"passed_time":0.09444461385,"remaining_time":3.538040534},
{"learn":[45.34344368],"iteration":26,"passed_time":0.09704355602,"remaining_time":3.497162222},
{"learn":[44.84120821],"iteration":27,"passed_time":0.09959967493,"remaining_time":3.457531572},
{"learn":[44.33524843],"iteration":28,"passed_time":0.1021559378,"remaining_time":3.420462608},
{"learn":[43.87569618],"iteration":29,"passed_time":0.1047214233,"remaining_time":3.385992688},
{"learn":[43.47711404],"iteration":30,"passed_time":0.1072057768,"remaining_time":3.351045088},
{"learn":[43.11511177],"iteration":31,"passed_time":0.1097410057,"remaining_time":3.319665423},
{"learn":[42.7351682],"iteration":32,"passed_time":0.1124319625,"remaining_time":3.294597204},
{"learn":[42.33342632],"iteration":33,"passed_time":0.1154519227,"remaining_time":3.280192861},
{"learn":[41.96224484],"iteration":34,"passed_time":0.1433175665,"remaining_time":3.951470047},
{"learn":[41.62010829],"iteration":35,"passed_time":0.1459425027,"remaining_time":3.908015907},
{"learn":[41.26826304],"iteration":36,"passed_time":0.1513454543,"remaining_time":3.939072231},
{"learn":[40.95481762],"iteration":37,"passed_time":0.1539671674,"remaining_time":3.897800395},
{"learn":[40.67758375],"iteration":38,"passed_time":0.1566574249,"remaining_time":3.860199625},
{"learn":[40.40407741],"iteration":39,"passed_time":0.1591870441,"remaining_time":3.820489059},
{"learn":[40.16937184],"iteration":40,"passed_time":0.1617965113,"remaining_time":3.784459862},
{"learn":[39.92568147],"iteration":41,"passed_time":0.1647075245,"remaining_time":3.756900201},
{"learn":[39.64931623],"iteration":42,"passed_time":0.1673995341,"remaining_time":3.725612887},
{"learn":[39.42280643],"iteration":43,"passed_time":0.1700626023,"remaining_time":3.694996542},
{"learn":[39.17148799],"iteration":44,"passed_time":0.172796288,"remaining_time":3.667121223},
{"learn":[38.97176033],"iteration":45,"passed_time":0.175810688,"remaining_time":3.646160791},
{"learn":[38.76723451],"iteration":46,"passed_time":0.1784420124,"remaining_time":3.61819655},
{"learn":[38.5718925],"iteration":47,"passed_time":0.1811355973,"remaining_time":3.592522679},
{"learn":[38.40445188],"iteration":48,"passed_time":0.1837051749,"remaining_time":3.565380026},
{"learn":[38.21937764],"iteration":49,"passed_time":0.1862934728,"remaining_time":3.539575983},
{"learn":[38.0448887],"iteration":50,"passed_time":0.1888579759,"remaining_time":3.514239591},
{"learn":[37.87489036],"iteration":51,"passed_time":0.191454086,"remaining_time":3.49035526},
{"learn":[37.7457846],"iteration":52,"passed_time":0.1952556561,"remaining_time":3.488813327},
{"learn":[37.59531839],"iteration":53,"passed_time":0.1978917222,"remaining_time":3.4667698},
{"learn":[37.42133558],"iteration":54,"passed_time":0.2004582781,"remaining_time":3.444237688},
{"learn":[37.26580342],"iteration":55,"passed_time":0.2031969831,"remaining_time":3.425320572},
{"learn":[37.11293518],"iteration":56,"passed_time":0.2057085835,"remaining_time":3.403213934},
{"learn":[36.98011769],"iteration":57,"passed_time":0.2081983747,"remaining_time":3.381428775},
{"learn":[36.82343878],"iteration":58,"passed_time":0.2109253482,"remaining_time":3.364080554},
{"learn":[36.67328938],"iteration":59,"passed_time":0.2148595058,"remaining_time":3.366132257},
{"learn":[36.53229726],"iteration":60,"passed_time":0.2455238341,"remaining_time":3.779457053},
{"learn":[36.40005639],"iteration":61,"passed_time":0.2483544817,"remaining_time":3.757362965},
{"learn":[36.2852783],"iteration":62,"passed_time":0.2510389455,"remaining_time":3.733706222},
{"learn":[36.17234642],"iteration":63,"passed_time":0.2535774841,"remaining_time":3.708570705},
{"learn":[36.06625116],"iteration":64,"passed_time":0.2561557379,"remaining_time":3.684701768},
{"learn":[35.93618861],"iteration":65,"passed_time":0.2587050062,"remaining_time":3.661067815},
{"learn":[35.83031638],"iteration":66,"passed_time":0.2612978723,"remaining_time":3.638670371},
{"learn":[35.74098278],"iteration":67,"passed_time":0.2637804081,"remaining_time":3.615343241},
{"learn":[35.65146132],"iteration":68,"passed_time":0.2663591995,"remaining_time":3.593919054},
{"learn":[35.55489572],"iteration":69,"passed_time":0.2689914455,"remaining_time":3.57374349},
{"learn":[35.46098435],"iteration":70,"passed_time":0.2716540697,"remaining_time":3.554459589},
{"learn":[35.38627141],"iteration":71,"passed_time":0.2742859278,"remaining_time":3.535240847},
{"learn":[35.29654506],"iteration":72,"passed_time":0.2768037891,"remaining_time":3.515028938},
{"learn":[35.21415915],"iteration":73,"passed_time":0.2793133479,"remaining_time":3.495191353},
{"learn":[35.130152],"iteration":74,"passed_time":0.2819198574,"remaining_time":3.477011575},
{"learn":[35.04138859],"iteration":75,"passed_time":0.2845858953,"remaining_time":3.459965359},
{"learn":[34.95812296],"iteration":76,"passed_time":0.2871862463,"remaining_time":3.442505264},
{"learn":[34.86941819],"iteration":77,"passed_time":0.2898789511,"remaining_time":3.426517858},
{"learn":[34.82086965],"iteration":78,"passed_time":0.2923084315,"remaining_time":3.407798296},
{"learn":[34.75193514],"iteration":79,"passed_time":0.2948755674,"remaining_time":3.391069026},
{"learn":[34.67772133],"iteration":80,"passed_time":0.2975362228,"remaining_time":3.375750479},
{"learn":[34.57842845],"iteration":81,"passed_time":0.3001189855,"remaining_time":3.359868642},
{"learn":[34.50456208],"iteration":82,"passed_time":0.303005087,"remaining_time":3.347658611},
{"learn":[34.42971934],"iteration":83,"passed_time":0.3057047959,"remaining_time":3.333638013},
{"learn":[34.35790589],"iteration":84,"passed_time":0.3083785196,"remaining_time":3.319604064},
{"learn":[34.28656925],"iteration":85,"passed_time":0.3110123328,"remaining_time":3.305410142},
{"learn":[34.21366492],"iteration":86,"passed_time":0.3135076657,"remaining_time":3.290028722},
{"learn":[34.15006873],"iteration":87,"passed_time":0.3401959493,"remaining_time":3.525667111},
{"learn":[34.08729504],"iteration":88,"passed_time":0.3430149446,"remaining_time":3.511085557},
{"learn":[34.02811668],"iteration":89,"passed_time":0.3456412673,"remaining_time":3.494817259},
{"learn":[33.94412236],"iteration":90,"passed_time":0.3483423811,"remaining_time":3.479595873},
{"learn":[33.8765895],"iteration":91,"passed_time":0.3510618105,"remaining_time":3.464827434},
{"learn":[33.81589641],"iteration":92,"passed_time":0.3536364402,"remaining_time":3.448905927},
{"learn":[33.75792381],"iteration":93,"passed_time":0.3563421941,"remaining_time":3.434532211},
{"learn":[33.71948065],"iteration":94,"passed_time":0.3588959305,"remaining_time":3.41895597},
{"learn":[33.66231886],"iteration":95,"passed_time":0.3613435617,"remaining_time":3.402651873},
{"learn":[33.58922864],"iteration":96,"passed_time":0.363939143,"remaining_time":3.388010785},
{"learn":[33.54512854],"iteration":97,"passed_time":0.36662079,"remaining_time":3.374407679},
{"learn":[33.48839948],"iteration":98,"passed_time":0.3692292691,"remaining_time":3.360359308},
{"learn":[33.45393274],"iteration":99,"passed_time":0.3717648652,"remaining_time":3.345883787},
{"learn":[33.41028486],"iteration":100,"passed_time":0.3742316752,"remaining_time":3.331032435},
{"learn":[33.36825457],"iteration":101,"passed_time":0.3768211604,"remaining_time":3.317503941},
{"learn":[33.30324968],"iteration":102,"passed_time":0.3794752012,"remaining_time":3.304750053},
{"learn":[33.24948787],"iteration":103,"passed_time":0.3820959662,"remaining_time":3.291903709},
{"learn":[33.19685537],"iteration":104,"passed_time":0.3847133343,"remaining_time":3.279223183},
{"learn":[33.14462364],"iteration":105,"passed_time":0.3873496228,"remaining_time":3.266892102},
{"learn":[33.09994679],"iteration":106,"passed_time":0.3899324503,"remaining_time":3.254296057},
{"learn":[33.06402425],"iteration":107,"passed_time":0.3924843867,"remaining_time":3.241630305},
{"learn":[33.01855784],"iteration":108,"passed_time":0.3950919635,"remaining_time":3.229604949},
{"learn":[32.96692593],"iteration":109,"passed_time":0.4007573123,"remaining_time":3.242490981},
{"learn":[32.92412962],"iteration":110,"passed_time":0.4036435658,"remaining_time":3.232784955},
{"learn":[32.87900695],"iteration":111,"passed_time":0.4063810267,"remaining_time":3.222020997},
{"learn":[32.83238972],"iteration":112,"passed_time":0.4091208381,"remaining_time":3.211417552},
{"learn":[32.77627735],"iteration":113,"passed_time":0.411848726,"remaining_time":3.200859397},
{"learn":[32.73202626],"iteration":114,"passed_time":0.442645261,"remaining_time":3.406443965},
{"learn":[32.68884341],"iteration":115,"passed_time":0.4452275748,"remaining_time":3.392941173},
{"learn":[32.65508241],"iteration":116,"passed_time":0.4480819293,"remaining_time":3.38167815},
{"learn":[32.62594079],"iteration":117,"passed_time":0.4506567637,"remaining_time":3.368468353},
{"learn":[32.59393488],"iteration":118,"passed_time":0.4532695062,"remaining_time":3.355717941},
{"learn":[32.55742467],"iteration":119,"passed_time":0.4557458667,"remaining_time":3.342136356},
{"learn":[32.52785622],"iteration":120,"passed_time":0.4583073585,"remaining_time":3.329356761},
{"learn":[32.45828724],"iteration":121,"passed_time":0.4608522148,"remaining_time":3.316624956},
{"learn":[32.40463889],"iteration":122,"passed_time":0.463563844,"remaining_time":3.305247896},
{"learn":[32.36743804],"iteration":123,"passed_time":0.4662158976,"remaining_time":3.293589728},
{"learn":[32.32354772],"iteration":124,"passed_time":0.4688781379,"remaining_time":3.282146965},
{"learn":[32.29592634],"iteration":125,"passed_time":0.4714058642,"remaining_time":3.269910518},
{"learn":[32.2603984],"iteration":126,"passed_time":0.4739795603,"remaining_time":3.258142961},
{"learn":[32.21485922],"iteration":127,"passed_time":0.4765989148,"remaining_time":3.246830107},
{"learn":[32.18081858],"iteration":128,"passed_time":0.4793358005,"remaining_time":3.236445599},
{"learn":[32.12551867],"iteration":129,"passed_time":0.4820552027,"remaining_time":3.226061741},
{"learn":[32.08599391],"iteration":130,"passed_time":0.4847103996,"remaining_time":3.215368987},
{"learn":[32.04639825],"iteration":131,"passed_time":0.4879009119,"remaining_time":3.208318118},
{"learn":[32.00877794],"iteration":132,"passed_time":0.490546483,"remaining_time":3.197772938},
{"learn":[31.97216121],"iteration":133,"passed_time":0.4932091857,"remaining_time":3.187456379},
{"learn":[31.93342304],"iteration":134,"passed_time":0.4958664882,"remaining_time":3.177218609},
{"learn":[31.89866565],"iteration":135,"passed_time":0.4985051111,"remaining_time":3.166973647},
{"learn":[31.86380354],"iteration":136,"passed_time":0.5010455937,"remaining_time":3.156221514},
{"learn":[31.832824],"iteration":137,"passed_time":0.5035769201,"remaining_time":3.145531197},
{"learn":[31.787381],"iteration":138,"passed_time":0.5061268645,"remaining_time":3.1350736},
{"learn":[31.76110501],"iteration":139,"passed_time":0.5087797118,"remaining_time":3.125361087},
{"learn":[31.71944852],"iteration":140,"passed_time":0.5117461709,"remaining_time":3.117659296},
{"learn":[31.69185087],"iteration":141,"passed_time":0.5383274995,"remaining_time":3.252711229},
{"learn":[31.65997931],"iteration":142,"passed_time":0.5411046372,"remaining_time":3.242843875},
{"learn":[31.63134055],"iteration":143,"passed_time":0.5437084482,"remaining_time":3.232044665},
{"learn":[31.60286303],"iteration":144,"passed_time":0.5463967074,"remaining_time":3.221856447},
{"learn":[31.55284718],"iteration":145,"passed_time":0.5490106851,"remaining_time":3.211336473},
{"learn":[31.50368292],"iteration":146,"passed_time":0.5517139021,"remaining_time":3.201441894},
{"learn":[31.46764929],"iteration":147,"passed_time":0.5543097858,"remaining_time":3.191026605},
{"learn":[31.4350197],"iteration":148,"passed_time":0.557000593,"remaining_time":3.18125842},
{"learn":[31.40769203],"iteration":149,"passed_time":0.559603912,"remaining_time":3.171088835},
{"learn":[31.36505545],"iteration":150,"passed_time":0.5621668023,"remaining_time":3.160792153},
{"learn":[31.33571282],"iteration":151,"passed_time":0.5647769783,"remaining_time":3.150861037},
{"learn":[31.30706225],"iteration":152,"passed_time":0.5673571497,"remaining_time":3.140859515},
{"learn":[31.27315751],"iteration":153,"passed_time":0.5700684629,"remaining_time":3.131674802},
{"learn":[31.24199032],"iteration":154,"passed_time":0.5727093603,"remaining_time":3.122189738},
{"learn":[31.22152495],"iteration":155,"passed_time":0.575248362,"remaining_time":3.112241138},
{"learn":[31.19359618],"iteration":156,"passed_time":0.5779207401,"remaining_time":3.103103082},
{"learn":[31.17468356],"iteration":157,"passed_time":0.5804345941,"remaining_time":3.093202078},
{"learn":[31.14623534],"iteration":158,"passed_time":0.5830122951,"remaining_time":3.083731699},
{"learn":[31.11270734],"iteration":159,"passed_time":0.5856063043,"remaining_time":3.074433098},
{"learn":[31.07944165],"iteration":160,"passed_time":0.5883898462,"remaining_time":3.066205472},
{"learn":[31.03747656],"iteration":161,"passed_time":0.5910479583,"remaining_time":3.057396229},
{"learn":[31.00938553],"iteration":162,"passed_time":0.5935782615,"remaining_time":3.048006165},
{"learn":[30.97848849],"iteration":163,"passed_time":0.5961722612,"remaining_time":3.039024453},
{"learn":[30.95160958],"iteration":164,"passed_time":0.598743338,"remaining_time":3.030004165},
{"learn":[30.92272439],"iteration":165,"passed_time":0.6013001289,"remaining_time":3.020989804},
{"learn":[30.90169128],"iteration":166,"passed_time":0.603773235,"remaining_time":3.011635358},
{"learn":[30.8733845],"iteration":167,"passed_time":0.606253358,"remaining_time":3.002397582},
{"learn":[30.83772402],"iteration":168,"passed_time":0.608887628,"remaining_time":2.993997745},
{"learn":[30.80838587],"iteration":169,"passed_time":0.6217297678,"remaining_time":3.03550416},
{"learn":[30.77682597],"iteration":170,"passed_time":0.6327875608,"remaining_time":3.067724491},
{"learn":[30.7297676],"iteration":171,"passed_time":0.6411514242,"remaining_time":3.086473135},
{"learn":[30.70423259],"iteration":172,"passed_time":0.643720905,"remaining_time":3.077209182},
{"learn":[30.6745014],"iteration":173,"passed_time":0.6482072048,"remaining_time":3.077121558},
{"learn":[30.64860303],"iteration":174,"passed_time":0.6507318438,"remaining_time":3.067735835},
{"learn":[30.62056966],"iteration":175,"passed_time":0.6532096388,"remaining_time":3.058208763},
{"learn":[30.59604521],"iteration":176,"passed_time":0.6557975423,"remaining_time":3.049273318},
{"learn":[30.5736101],"iteration":177,"passed_time":0.658412908,"remaining_time":3.040536013},
{"learn":[30.54525065],"iteration":178,"passed_time":0.66104393,"remaining_time":3.031938919},
{"learn":[30.51598901],"iteration":179,"passed_time":0.6635263107,"remaining_time":3.022730971},
{"learn":[30.49490014],"iteration":180,"passed_time":0.6660589331,"remaining_time":3.013824675},
{"learn":[30.46155624],"iteration":181,"passed_time":0.6686474263,"remaining_time":3.005239531},
{"learn":[30.43198255],"iteration":182,"passed_time":0.6713088417,"remaining_time":2.997045484},
{"learn":[30.38983022],"iteration":183,"passed_time":0.6739555984,"remaining_time":2.988846567},
{"learn":[30.37233187],"iteration":184,"passed_time":0.6765486084,"remaining_time":2.980470897},
{"learn":[30.33922317],"iteration":185,"passed_time":0.6790912943,"remaining_time":2.97193717},
{"learn":[30.29677146],"iteration":186,"passed_time":0.681717105,"remaining_time":2.963828911},
{"learn":[30.27556231],"iteration":187,"passed_time":0.6843406908,"remaining_time":2.955769367},
{"learn":[30.25032918],"iteration":188,"passed_time":0.6868581626,"remaining_time":2.94731201},
{"learn":[30.22446188],"iteration":189,"passed_time":0.689670301,"remaining_time":2.940173388},
{"learn":[30.20082508],"iteration":190,"passed_time":0.6922486163,"remaining_time":2.932089689},
{"learn":[30.16501865],"iteration":191,"passed_time":0.6949586343,"remaining_time":2.924617586},
{"learn":[30.12997274],"iteration":192,"passed_time":0.697522147,"remaining_time":2.916582241},
{"learn":[30.10602095],"iteration":193,"passed_time":0.7000352562,"remaining_time":2.9083939},
{"learn":[30.08080356],"iteration":194,"passed_time":0.7026311079,"remaining_time":2.900605343},
{"learn":[30.04486991],"iteration":195,"passed_time":0.7051855292,"remaining_time":2.892699824},
{"learn":[30.02113873],"iteration":196,"passed_time":0.7078250298,"remaining_time":2.885195426},
{"learn":[29.99657949],"iteration":197,"passed_time":0.7342695341,"remaining_time":2.974162456},
{"learn":[29.98169892],"iteration":198,"passed_time":0.7375234597,"remaining_time":2.968624579},
{"learn":[29.96511253],"iteration":199,"passed_time":0.7401437207,"remaining_time":2.960574883},
{"learn":[29.93590005],"iteration":200,"passed_time":0.7428085353,"remaining_time":2.952756317},
{"learn":[29.91548146],"iteration":201,"passed_time":0.745292868,"remaining_time":2.944275785},
{"learn":[29.89247812],"iteration":202,"passed_time":0.7478575527,"remaining_time":2.9361698},
{"learn":[29.86641387],"iteration":203,"passed_time":0.7504412025,"remaining_time":2.928192143},
{"learn":[29.84427364],"iteration":204,"passed_time":0.7529598287,"remaining_time":2.920014945},
{"learn":[29.82500436],"iteration":205,"passed_time":0.7555304343,"remaining_time":2.912093033},
{"learn":[29.80260266],"iteration":206,"passed_time":0.758125186,"remaining_time":2.904315326},
{"learn":[29.78433513],"iteration":207,"passed_time":0.7605273186,"remaining_time":2.895854021},
{"learn":[29.76008592],"iteration":208,"passed_time":0.7630938505,"remaining_time":2.888072898},
{"learn":[29.7370788],"iteration":209,"passed_time":0.7657298287,"remaining_time":2.880602689},
{"learn":[29.70209944],"iteration":210,"passed_time":0.7683835831,"remaining_time":2.873244773},
{"learn":[29.67320928],"iteration":211,"passed_time":0.770931265,"remaining_time":2.865536966},
{"learn":[29.65131133],"iteration":212,"passed_time":0.7734472712,"remaining_time":2.857760575},
{"learn":[29.62516151],"iteration":213,"passed_time":0.7760788436,"remaining_time":2.850457809},
{"learn":[29.60682583],"iteration":214,"passed_time":0.7785908752,"remaining_time":2.842762033},
{"learn":[29.58890359],"iteration":215,"passed_time":0.7811186335,"remaining_time":2.835171337},
{"learn":[29.55631739],"iteration":216,"passed_time":0.7837930132,"remaining_time":2.828156356},
{"learn":[29.52733485],"iteration":217,"passed_time":0.7864578191,"remaining_time":2.821146856},
{"learn":[29.51308007],"iteration":218,"passed_time":0.7887980257,"remaining_time":2.813019443},
{"learn":[29.49515949],"iteration":219,"passed_time":0.7913816652,"remaining_time":2.805807722},
{"learn":[29.47200848],"iteration":220,"passed_time":0.7939062874,"remaining_time":2.798429855},
{"learn":[29.44052978],"iteration":221,"passed_time":0.7964354786,"remaining_time":2.791111722},
{"learn":[29.41105531],"iteration":222,"passed_time":0.7990060498,"remaining_time":2.783980721},
{"learn":[29.39232256],"iteration":223,"passed_time":0.8014915041,"remaining_time":2.776595568},
{"learn":[29.36873665],"iteration":224,"passed_time":0.8040988192,"remaining_time":2.769673711},
{"learn":[29.35079785],"iteration":225,"passed_time":0.8065897265,"remaining_time":2.762391364},
{"learn":[29.32464736],"iteration":226,"passed_time":0.8132639522,"remaining_time":2.76939663},
{"learn":[29.29857723],"iteration":227,"passed_time":0.8222261411,"remaining_time":2.784028864},
{"learn":[29.27374113],"iteration":228,"passed_time":0.8345212964,"remaining_time":2.809676504},
{"learn":[29.25343619],"iteration":229,"passed_time":0.8393166527,"remaining_time":2.809886185},
{"learn":[29.23773772],"iteration":230,"passed_time":0.8419015674,"remaining_time":2.802693962},
{"learn":[29.21651077],"iteration":231,"passed_time":0.8445494881,"remaining_time":2.79575003},
{"learn":[29.2005638],"iteration":232,"passed_time":0.8473528575,"remaining_time":2.789354686},
{"learn":[29.17426621],"iteration":233,"passed_time":0.849906134,"remaining_time":2.782171362},
{"learn":[29.15534308],"iteration":234,"passed_time":0.8524143551,"remaining_time":2.774880773},
{"learn":[29.12889509],"iteration":235,"passed_time":0.8550560134,"remaining_time":2.768062687},
{"learn":[29.1089564],"iteration":236,"passed_time":0.8576566028,"remaining_time":2.761147628},
{"learn":[29.09435114],"iteration":237,"passed_time":0.8600341365,"remaining_time":2.753554672},
{"learn":[29.07442402],"iteration":238,"passed_time":0.8626707546,"remaining_time":2.746830311},
{"learn":[29.05393654],"iteration":239,"passed_time":0.8651989338,"remaining_time":2.739796624},
{"learn":[29.03759155],"iteration":240,"passed_time":0.867771321,"remaining_time":2.732939555},
{"learn":[29.02369678],"iteration":241,"passed_time":0.8703223574,"remaining_time":2.72605102},
{"learn":[29.0023563],"iteration":242,"passed_time":0.8732520654,"remaining_time":2.720377833},
{"learn":[28.97851566],"iteration":243,"passed_time":0.8761516511,"remaining_time":2.714633804},
{"learn":[28.95786014],"iteration":244,"passed_time":0.878835387,"remaining_time":2.708247825},
{"learn":[28.94454106],"iteration":245,"passed_time":0.8814431781,"remaining_time":2.701659172},
{"learn":[28.92509124],"iteration":246,"passed_time":0.8840308745,"remaining_time":2.695041492},
{"learn":[28.90240291],"iteration":247,"passed_time":0.886681444,"remaining_time":2.688646959},
{"learn":[28.88156536],"iteration":248,"passed_time":0.8894124656,"remaining_time":2.682525147},
{"learn":[28.8590183],"iteration":249,"passed_time":0.8921998156,"remaining_time":2.676599447},
{"learn":[28.8456239],"iteration":250,"passed_time":0.8947022718,"remaining_time":2.669848612},
{"learn":[28.83032804],"iteration":251,"passed_time":0.8971886685,"remaining_time":2.663083826},
{"learn":[28.81700165],"iteration":252,"passed_time":0.8997976509,"remaining_time":2.656714803},
{"learn":[28.7931215],"iteration":253,"passed_time":0.9024502357,"remaining_time":2.650503448},
{"learn":[28.77472609],"iteration":254,"passed_time":0.9051065486,"remaining_time":2.644330897},
{"learn":[28.74988964],"iteration":255,"passed_time":0.9158234013,"remaining_time":2.66161176},
{"learn":[28.72380979],"iteration":256,"passed_time":0.9293141548,"remaining_time":2.68669423},
{"learn":[28.70401335],"iteration":257,"passed_time":0.9384702283,"remaining_time":2.699011277},
{"learn":[28.68622667],"iteration":258,"passed_time":0.9415604947,"remaining_time":2.693808211},
{"learn":[28.66519323],"iteration":259,"passed_time":0.9442335935,"remaining_time":2.687434074},
{"learn":[28.64422899],"iteration":260,"passed_time":0.9467903436,"remaining_time":2.680758866},
{"learn":[28.62557673],"iteration":261,"passed_time":0.949370631,"remaining_time":2.674181396},
{"learn":[28.61034577],"iteration":262,"passed_time":0.9519851823,"remaining_time":2.66773034},
{"learn":[28.59317029],"iteration":263,"passed_time":0.9546034352,"remaining_time":2.661318668},
{"learn":[28.57056916],"iteration":264,"passed_time":0.9571517188,"remaining_time":2.65474156},
{"learn":[28.54249241],"iteration":265,"passed_time":0.9598037924,"remaining_time":2.648481142},
{"learn":[28.52767974],"iteration":266,"passed_time":0.9624749512,"remaining_time":2.642300147},
{"learn":[28.50474258],"iteration":267,"passed_time":0.9650775183,"remaining_time":2.635957998},
{"learn":[28.48990946],"iteration":268,"passed_time":0.9676542928,"remaining_time":2.629573561},
{"learn":[28.46196239],"iteration":269,"passed_time":0.9702261544,"remaining_time":2.623204047},
{"learn":[28.44243842],"iteration":270,"passed_time":0.972917476,"remaining_time":2.617183911},
{"learn":[28.42121272],"iteration":271,"passed_time":0.9755141973,"remaining_time":2.610935058},
{"learn":[28.40043506],"iteration":272,"passed_time":0.9781950475,"remaining_time":2.604936995},
{"learn":[28.38568819],"iteration":273,"passed_time":0.9808192782,"remaining_time":2.598813124},
{"learn":[28.35607503],"iteration":274,"passed_time":0.983510471,"remaining_time":2.592891242},
{"learn":[28.33951915],"iteration":275,"passed_time":0.9860928648,"remaining_time":2.58670737},
{"learn":[28.32454538],"iteration":276,"passed_time":0.9886829412,"remaining_time":2.580569554},
{"learn":[28.31172935],"iteration":277,"passed_time":0.9911769781,"remaining_time":2.574207835},
{"learn":[28.29422179],"iteration":278,"passed_time":0.9940100993,"remaining_time":2.568750113},
{"learn":[28.27848751],"iteration":279,"passed_time":0.9967999757,"remaining_time":2.563199937},
{"learn":[28.26640461],"iteration":280,"passed_time":0.9993173794,"remaining_time":2.556972227},
{"learn":[28.25240043],"iteration":281,"passed_time":1.00189022,"remaining_time":2.550911979},
{"learn":[28.23319502],"iteration":282,"passed_time":1.004495346,"remaining_time":2.544958173},
{"learn":[28.21633727],"iteration":283,"passed_time":1.010175935,"remaining_time":2.546781582},
{"learn":[28.19245859],"iteration":284,"passed_time":1.021134764,"remaining_time":2.561794233},
{"learn":[28.17515255],"iteration":285,"passed_time":1.027041965,"remaining_time":2.564013857},
{"learn":[28.16100504],"iteration":286,"passed_time":1.035687713,"remaining_time":2.572980276},
{"learn":[28.14755775],"iteration":287,"passed_time":1.038720567,"remaining_time":2.567948069},
{"learn":[28.13465067],"iteration":288,"passed_time":1.041191292,"remaining_time":2.561546742},
{"learn":[28.11794773],"iteration":289,"passed_time":1.043779337,"remaining_time":2.555459756},
{"learn":[28.08794435],"iteration":290,"passed_time":1.046448502,"remaining_time":2.549594461},
{"learn":[28.06361682],"iteration":291,"passed_time":1.049118771,"remaining_time":2.543753733},
{"learn":[28.04454315],"iteration":292,"passed_time":1.051718326,"remaining_time":2.537764016},
{"learn":[28.03182915],"iteration":293,"passed_time":1.054149035,"remaining_time":2.5313919},
{"learn":[28.01730281],"iteration":294,"passed_time":1.05679544,"remaining_time":2.525561984},
{"learn":[27.99234983],"iteration":295,"passed_time":1.059677703,"remaining_time":2.520314537},
{"learn":[27.97813178],"iteration":296,"passed_time":1.062131817,"remaining_time":2.514069587},
{"learn":[27.96477035],"iteration":297,"passed_time":1.064710662,"remaining_time":2.508143908},
{"learn":[27.95160803],"iteration":298,"passed_time":1.067264913,"remaining_time":2.502182956},
{"learn":[27.93790182],"iteration":299,"passed_time":1.06986402,"remaining_time":2.496349379},
{"learn":[27.92128831],"iteration":300,"passed_time":1.072464851,"remaining_time":2.4905413},
{"learn":[27.898933],"iteration":301,"passed_time":1.075102855,"remaining_time":2.484840374},
{"learn":[27.88404285],"iteration":302,"passed_time":1.077577837,"remaining_time":2.478784662},
{"learn":[27.86637553],"iteration":303,"passed_time":1.080218891,"remaining_time":2.473132724},
{"learn":[27.85174232],"iteration":304,"passed_time":1.082929062,"remaining_time":2.467658025},
{"learn":[27.83716131],"iteration":305,"passed_time":1.085527754,"remaining_time":2.461948566},
{"learn":[27.82179779],"iteration":306,"passed_time":1.088233708,"remaining_time":2.456501497},
{"learn":[27.80839014],"iteration":307,"passed_time":1.090748089,"remaining_time":2.450641811},
{"learn":[27.79578788],"iteration":308,"passed_time":1.093223491,"remaining_time":2.444716608},
{"learn":[27.78185873],"iteration":309,"passed_time":1.095731844,"remaining_time":2.438887007},
{"learn":[27.76113739],"iteration":310,"passed_time":1.098323388,"remaining_time":2.433263069},
{"learn":[27.74286822],"iteration":311,"passed_time":1.100897553,"remaining_time":2.427620245},
{"learn":[27.72955462],"iteration":312,"passed_time":1.103593686,"remaining_time":2.422264735},
{"learn":[27.71042019],"iteration":313,"passed_time":1.107706213,"remaining_time":2.420020581},
{"learn":[27.69275975],"iteration":314,"passed_time":1.111981736,"remaining_time":2.418119014},
{"learn":[27.68134751],"iteration":315,"passed_time":1.115397548,"remaining_time":2.414341528},
{"learn":[27.6601989],"iteration":316,"passed_time":1.11914315,"remaining_time":2.411276882},
{"learn":[27.64232941],"iteration":317,"passed_time":1.122280949,"remaining_time":2.406904426},
{"learn":[27.62172678],"iteration":318,"passed_time":1.126152011,"remaining_time":2.404105077},
{"learn":[27.60497213],"iteration":319,"passed_time":1.130039194,"remaining_time":2.401333288},
{"learn":[27.58384259],"iteration":320,"passed_time":1.133856985,"remaining_time":2.398407765},
{"learn":[27.56331091],"iteration":321,"passed_time":1.137584655,"remaining_time":2.395286944},
{"learn":[27.54211166],"iteration":322,"passed_time":1.14123385,"remaining_time":2.391997884},
{"learn":[27.53021271],"iteration":323,"passed_time":1.144419607,"remaining_time":2.387739674},
{"learn":[27.51637589],"iteration":324,"passed_time":1.147018239,"remaining_time":2.38226865},
{"learn":[27.49524565],"iteration":325,"passed_time":1.1497571,"remaining_time":2.377105169},
{"learn":[27.48341772],"iteration":326,"passed_time":1.15238861,"remaining_time":2.371735579},
{"learn":[27.46443062],"iteration":327,"passed_time":1.154920781,"remaining_time":2.366179161},
{"learn":[27.44949503],"iteration":328,"passed_time":1.157485418,"remaining_time":2.360707343},
{"learn":[27.43175046],"iteration":329,"passed_time":1.160136494,"remaining_time":2.35542864},
{"learn":[27.4193855],"iteration":330,"passed_time":1.162618684,"remaining_time":2.34982447},
{"learn":[27.40440375],"iteration":331,"passed_time":1.165250972,"remaining_time":2.344541111},
{"learn":[27.392239],"iteration":332,"passed_time":1.167780512,"remaining_time":2.339067873},
{"learn":[27.38255745],"iteration":333,"passed_time":1.17094895,"remaining_time":2.334886229},
{"learn":[27.37064615],"iteration":334,"passed_time":1.173658241,"remaining_time":2.329799196},
{"learn":[27.35894911],"iteration":335,"passed_time":1.177077093,"remaining_time":2.32612854},
{"learn":[27.33925499],"iteration":336,"passed_time":1.17987738,"remaining_time":2.321242443},
{"learn":[27.32770301],"iteration":337,"passed_time":1.182410252,"remaining_time":2.315844932},
{"learn":[27.31040026],"iteration":338,"passed_time":1.185000586,"remaining_time":2.310576365},
{"learn":[27.29713466],"iteration":339,"passed_time":1.187630161,"remaining_time":2.305399725},
{"learn":[27.28579117],"iteration":340,"passed_time":1.190204544,"remaining_time":2.300131362},
{"learn":[27.27027493],"iteration":341,"passed_time":1.192922307,"remaining_time":2.295154613},
{"learn":[27.25936349],"iteration":342,"passed_time":1.195528611,"remaining_time":2.289977544},
{"learn":[27.23796238],"iteration":343,"passed_time":1.1987502,"remaining_time":2.285988753},
{"learn":[27.22769026],"iteration":344,"passed_time":1.201634079,"remaining_time":2.281363252},
{"learn":[27.216073],"iteration":345,"passed_time":1.205594771,"remaining_time":2.27878318},
{"learn":[27.20001325],"iteration":346,"passed_time":1.209390743,"remaining_time":2.275885174},
{"learn":[27.18701536],"iteration":347,"passed_time":1.212709677,"remaining_time":2.272088245},
{"learn":[27.17369513],"iteration":348,"passed_time":1.216713354,"remaining_time":2.269571328},
{"learn":[27.1607258],"iteration":349,"passed_time":1.220531182,"remaining_time":2.266700767},
{"learn":[27.14458939],"iteration":350,"passed_time":1.224415747,"remaining_time":2.263948204},
{"learn":[27.12974275],"iteration":351,"passed_time":1.228232633,"remaining_time":2.26106462},
{"learn":[27.11609923],"iteration":352,"passed_time":1.232241507,"remaining_time":2.258527634},
{"learn":[27.09799455],"iteration":353,"passed_time":1.236314526,"remaining_time":2.256099389},
{"learn":[27.0773285],"iteration":354,"passed_time":1.240384462,"remaining_time":2.253656277},
{"learn":[27.06310922],"iteration":355,"passed_time":1.24426815,"remaining_time":2.250867103},
{"learn":[27.04928057],"iteration":356,"passed_time":1.24713002,"remaining_time":2.24623138},
{"learn":[27.03569388],"iteration":357,"passed_time":1.249639017,"remaining_time":2.240972762},
{"learn":[27.02195855],"iteration":358,"passed_time":1.252178512,"remaining_time":2.235783916},
{"learn":[27.00984674],"iteration":359,"passed_time":1.254706488,"remaining_time":2.230589313},
{"learn":[26.99925505],"iteration":360,"passed_time":1.257344327,"remaining_time":2.225603948},
{"learn":[26.98035389],"iteration":361,"passed_time":1.259996934,"remaining_time":2.220657579},
{"learn":[26.96620626],"iteration":362,"passed_time":1.262643255,"remaining_time":2.21571282},
{"learn":[26.95769653],"iteration":363,"passed_time":1.265363076,"remaining_time":2.210909111},
{"learn":[26.94059596],"iteration":364,"passed_time":1.267952587,"remaining_time":2.205890118},
{"learn":[26.92908997],"iteration":365,"passed_time":1.270755498,"remaining_time":2.20125406},
{"learn":[26.91921293],"iteration":366,"passed_time":1.273455922,"remaining_time":2.196451222},
{"learn":[26.90694011],"iteration":367,"passed_time":1.275913496,"remaining_time":2.191242742},
{"learn":[26.88826547],"iteration":368,"passed_time":1.278511642,"remaining_time":2.186289555},
{"learn":[26.87897585],"iteration":369,"passed_time":1.281028997,"remaining_time":2.181211535},
{"learn":[26.86441732],"iteration":370,"passed_time":1.283640277,"remaining_time":2.176306561},
{"learn":[26.84675176],"iteration":371,"passed_time":1.286339341,"remaining_time":2.171562113},
{"learn":[26.83228303],"iteration":372,"passed_time":1.28892649,"remaining_time":2.166640507},
{"learn":[26.81896359],"iteration":373,"passed_time":1.291697719,"remaining_time":2.162039497},
{"learn":[26.80522499],"iteration":374,"passed_time":1.294293201,"remaining_time":2.157155335},
{"learn":[26.7932732],"iteration":375,"passed_time":1.296851193,"remaining_time":2.152221129},
{"learn":[26.7856749],"iteration":376,"passed_time":1.299312558,"remaining_time":2.14713985},
{"learn":[26.77243344],"iteration":377,"passed_time":1.302259864,"remaining_time":2.142872052},
{"learn":[26.76126513],"iteration":378,"passed_time":1.305620233,"remaining_time":2.139288033},
{"learn":[26.75004285],"iteration":379,"passed_time":1.309042151,"remaining_time":2.135805615},
{"learn":[26.73787729],"iteration":380,"passed_time":1.312325695,"remaining_time":2.132098702},
{"learn":[26.72970586],"iteration":381,"passed_time":1.315442671,"remaining_time":2.12812453},
{"learn":[26.71372265],"iteration":382,"passed_time":1.318965935,"remaining_time":2.124809352},
{"learn":[26.69693489],"iteration":383,"passed_time":1.322341902,"remaining_time":2.121256801},
{"learn":[26.68283413],"iteration":384,"passed_time":1.326171817,"remaining_time":2.118430304},
{"learn":[26.66812221],"iteration":385,"passed_time":1.329893504,"remaining_time":2.115426455},
{"learn":[26.65421085],"iteration":386,"passed_time":1.33336798,"remaining_time":2.112027317},
{"learn":[26.64568448],"iteration":387,"passed_time":1.336962365,"remaining_time":2.108816926},
{"learn":[26.63151817],"iteration":388,"passed_time":1.340062292,"remaining_time":2.104827919},
{"learn":[26.61987243],"iteration":389,"passed_time":1.343510991,"remaining_time":2.101388985},
{"learn":[26.61028965],"iteration":390,"passed_time":1.34651853,"remaining_time":2.097262876},
{"learn":[26.59105011],"iteration":391,"passed_time":1.349122782,"remaining_time":2.092516969},
{"learn":[26.58030743],"iteration":392,"passed_time":1.351697003,"remaining_time":2.087735575},
{"learn":[26.56425289],"iteration":393,"passed_time":1.354317854,"remaining_time":2.083037105},
{"learn":[26.54699728],"iteration":394,"passed_time":1.357146977,"remaining_time":2.078668154},
{"learn":[26.53471528],"iteration":395,"passed_time":1.359772597,"remaining_time":2.073996587},
{"learn":[26.52184563],"iteration":396,"passed_time":1.362318772,"remaining_time":2.069214658},
{"learn":[26.51133752],"iteration":397,"passed_time":1.364884765,"remaining_time":2.064473941},
{"learn":[26.50062708],"iteration":398,"passed_time":1.367400013,"remaining_time":2.059667689},
{"learn":[26.49227262],"iteration":399,"passed_time":1.370027162,"remaining_time":2.055040743},
{"learn":[26.47737694],"iteration":400,"passed_time":1.372613658,"remaining_time":2.050363045},
{"learn":[26.46752589],"iteration":401,"passed_time":1.375177579,"remaining_time":2.04566217},
{"learn":[26.46093485],"iteration":402,"passed_time":1.377665894,"remaining_time":2.040859898},
{"learn":[26.45036706],"iteration":403,"passed_time":1.380196941,"remaining_time":2.036132121},
{"learn":[26.43616792],"iteration":404,"passed_time":1.382834583,"remaining_time":2.031571794},
{"learn":[26.4222386],"iteration":405,"passed_time":1.385679795,"remaining_time":2.027324626},
{"learn":[26.41177607],"iteration":406,"passed_time":1.388250938,"remaining_time":2.022685027},
{"learn":[26.39915188],"iteration":407,"passed_time":1.390750266,"remaining_time":2.017951366},
{"learn":[26.3832357],"iteration":408,"passed_time":1.393404913,"remaining_time":2.013453065},
{"learn":[26.3692162],"iteration":409,"passed_time":1.395947912,"remaining_time":2.008803093},
{"learn":[26.35646128],"iteration":410,"passed_time":1.398533605,"remaining_time":2.004224558},
{"learn":[26.34485894],"iteration":411,"passed_time":1.401823859,"remaining_time":2.000661236},
{"learn":[26.32887151],"iteration":412,"passed_time":1.405715407,"remaining_time":1.99795386},
{"learn":[26.31873666],"iteration":413,"passed_time":1.408819243,"remaining_time":1.994125789},
{"learn":[26.30815914],"iteration":414,"passed_time":1.411991483,"remaining_time":1.990397633},
{"learn":[26.28962432],"iteration":415,"passed_time":1.415420401,"remaining_time":1.987032485},
{"learn":[26.27986581],"iteration":416,"passed_time":1.418347895,"remaining_time":1.982966002},
{"learn":[26.26642951],"iteration":417,"passed_time":1.425212649,"remaining_time":1.98438699},
{"learn":[26.2545534],"iteration":418,"passed_time":1.428228412,"remaining_time":1.980431283},
{"learn":[26.24186303],"iteration":419,"passed_time":1.431445582,"remaining_time":1.976758185},
{"learn":[26.23240219],"iteration":420,"passed_time":1.434798379,"remaining_time":1.973273781},
{"learn":[26.22119939],"iteration":421,"passed_time":1.437825839,"remaining_time":1.969344395},
{"learn":[26.20956638],"iteration":422,"passed_time":1.440782874,"remaining_time":1.965323212},
{"learn":[26.19944073],"iteration":423,"passed_time":1.444094435,"remaining_time":1.961788666},
{"learn":[26.18473382],"iteration":424,"passed_time":1.447128118,"remaining_time":1.957879219},
{"learn":[26.1750729],"iteration":425,"passed_time":1.45005612,"remaining_time":1.953831486},
{"learn":[26.15984455],"iteration":426,"passed_time":1.452973918,"remaining_time":1.949775305},
{"learn":[26.14782114],"iteration":427,"passed_time":1.455580356,"remaining_time":1.945308326},
{"learn":[26.13264506],"iteration":428,"passed_time":1.458166209,"remaining_time":1.940822623},
{"learn":[26.12180676],"iteration":429,"passed_time":1.460709347,"remaining_time":1.936289135},
{"learn":[26.10574571],"iteration":430,"passed_time":1.463347628,"remaining_time":1.931890488},
{"learn":[26.09252139],"iteration":431,"passed_time":1.465874201,"remaining_time":1.927353116},
{"learn":[26.08435013],"iteration":432,"passed_time":1.468341255,"remaining_time":1.922747093},
{"learn":[26.07287766],"iteration":433,"passed_time":1.471180866,"remaining_time":1.918636798},
{"learn":[26.05951573],"iteration":434,"passed_time":1.473929248,"remaining_time":1.914413851},
{"learn":[26.04852399],"iteration":435,"passed_time":1.476451483,"remaining_time":1.909905129},
{"learn":[26.03565499],"iteration":436,"passed_time":1.479440951,"remaining_time":1.906007449},
{"learn":[26.02606009],"iteration":437,"passed_time":1.482012403,"remaining_time":1.901577558},
{"learn":[26.01857136],"iteration":438,"passed_time":1.484509427,"remaining_time":1.897061022},
{"learn":[26.00001095],"iteration":439,"passed_time":1.487096316,"remaining_time":1.892668039},
{"learn":[25.985398],"iteration":440,"passed_time":1.489530637,"remaining_time":1.888089855},
{"learn":[25.97206595],"iteration":441,"passed_time":1.492138284,"remaining_time":1.883740186},
{"learn":[25.95873047],"iteration":442,"passed_time":1.494735676,"remaining_time":1.879385489},
{"learn":[25.94445893],"iteration":443,"passed_time":1.497315131,"remaining_time":1.875016245},
{"learn":[25.93687022],"iteration":444,"passed_time":1.500047344,"remaining_time":1.870845564},
{"learn":[25.92571783],"iteration":445,"passed_time":1.502654528,"remaining_time":1.866526028},
{"learn":[25.91333064],"iteration":446,"passed_time":1.505269292,"remaining_time":1.862223532},
{"learn":[25.90397058],"iteration":447,"passed_time":1.5079062,"remaining_time":1.857955854},
{"learn":[25.88773817],"iteration":448,"passed_time":1.510644673,"remaining_time":1.853820078},
{"learn":[25.8817299],"iteration":449,"passed_time":1.51327533,"remaining_time":1.849558736},
{"learn":[25.86874764],"iteration":450,"passed_time":1.515950304,"remaining_time":1.845358575},
{"learn":[25.85892161],"iteration":451,"passed_time":1.518506321,"remaining_time":1.841020938},
{"learn":[25.8466708],"iteration":452,"passed_time":1.521132648,"remaining_time":1.836776068},
{"learn":[25.83578084],"iteration":453,"passed_time":1.523852983,"remaining_time":1.832651385},
{"learn":[25.82307674],"iteration":454,"passed_time":1.526530591,"remaining_time":1.828481697},
{"learn":[25.80784263],"iteration":455,"passed_time":1.529205988,"remaining_time":1.824315915},
{"learn":[25.79723981],"iteration":456,"passed_time":1.531843833,"remaining_time":1.820112038},
{"learn":[25.78462557],"iteration":457,"passed_time":1.537047708,"remaining_time":1.818951654},
{"learn":[25.76971866],"iteration":458,"passed_time":1.539891567,"remaining_time":1.814992021},
{"learn":[25.75731206],"iteration":459,"passed_time":1.542597998,"remaining_time":1.810875911},
{"learn":[25.74639863],"iteration":460,"passed_time":1.54518633,"remaining_time":1.806627835},
{"learn":[25.73550714],"iteration":461,"passed_time":1.547770747,"remaining_time":1.802382385},
{"learn":[25.72787098],"iteration":462,"passed_time":1.550401656,"remaining_time":1.798198033},
{"learn":[25.71830439],"iteration":463,"passed_time":1.553092765,"remaining_time":1.794089918},
{"learn":[25.7053927],"iteration":464,"passed_time":1.555828279,"remaining_time":1.790038987},
{"learn":[25.69522642],"iteration":465,"passed_time":1.558501686,"remaining_time":1.785922533},
{"learn":[25.68795462],"iteration":466,"passed_time":1.561165437,"remaining_time":1.781801237},
{"learn":[25.6775392],"iteration":467,"passed_time":1.564423551,"remaining_time":1.778361815},
{"learn":[25.66528016],"iteration":468,"passed_time":1.567756708,"remaining_time":1.775008128},
{"learn":[25.65335672],"iteration":469,"passed_time":1.571401141,"remaining_time":1.772005542},
{"learn":[25.64255639],"iteration":470,"passed_time":1.574707711,"remaining_time":1.768620763},
{"learn":[25.6327354],"iteration":471,"passed_time":1.577631623,"remaining_time":1.764808257},
{"learn":[25.61970209],"iteration":472,"passed_time":1.580352767,"remaining_time":1.76077359},
{"learn":[25.61003537],"iteration":473,"passed_time":1.582941047,"remaining_time":1.756597026},
{"learn":[25.60435428],"iteration":474,"passed_time":1.585456733,"remaining_time":1.752346915},
{"learn":[25.59488367],"iteration":475,"passed_time":1.58804188,"remaining_time":1.748180557},
{"learn":[25.58673566],"iteration":476,"passed_time":1.590618531,"remaining_time":1.744011513},
{"learn":[25.57017504],"iteration":477,"passed_time":1.593233333,"remaining_time":1.739890795},
{"learn":[25.5622144],"iteration":478,"passed_time":1.595791112,"remaining_time":1.735714341},
{"learn":[25.55512366],"iteration":479,"passed_time":1.600454539,"remaining_time":1.73382575},
{"learn":[25.54237686],"iteration":480,"passed_time":1.60931297,"remaining_time":1.736452041},
{"learn":[25.5266777],"iteration":481,"passed_time":1.615623406,"remaining_time":1.736292374},
{"learn":[25.51597083],"iteration":482,"passed_time":1.619039334,"remaining_time":1.733008976},
{"learn":[25.50555493],"iteration":483,"passed_time":1.622349439,"remaining_time":1.729612212},
{"learn":[25.48844176],"iteration":484,"passed_time":1.625734875,"remaining_time":1.726295795},
{"learn":[25.47577211],"iteration":485,"passed_time":1.628917826,"remaining_time":1.722764943},
{"learn":[25.46264165],"iteration":486,"passed_time":1.631883593,"remaining_time":1.719006741},
{"learn":[25.45378055],"iteration":487,"passed_time":1.634740446,"remaining_time":1.715137517},
{"learn":[25.43905639],"iteration":488,"passed_time":1.637386351,"remaining_time":1.711051995},
{"learn":[25.42638091],"iteration":489,"passed_time":1.640063857,"remaining_time":1.707005239},
{"learn":[25.41363952],"iteration":490,"passed_time":1.642716266,"remaining_time":1.702938044},
{"learn":[25.40441568],"iteration":491,"passed_time":1.645328392,"remaining_time":1.698835007},
{"learn":[25.39546935],"iteration":492,"passed_time":1.647884656,"remaining_time":1.694680569},
{"learn":[25.38482402],"iteration":493,"passed_time":1.650492233,"remaining_time":1.690585162},
{"learn":[25.37446767],"iteration":494,"passed_time":1.653095498,"remaining_time":1.686491366},
{"learn":[25.36486381],"iteration":495,"passed_time":1.655681599,"remaining_time":1.682386141},
{"learn":[25.35698719],"iteration":496,"passed_time":1.658311021,"remaining_time":1.678330872},
{"learn":[25.34321008],"iteration":497,"passed_time":1.661058332,"remaining_time":1.674400166},
{"learn":[25.32844178],"iteration":498,"passed_time":1.663866053,"remaining_time":1.670534855},
{"learn":[25.31911864],"iteration":499,"passed_time":1.666429766,"remaining_time":1.666429766},
{"learn":[25.31191379],"iteration":500,"passed_time":1.668984851,"remaining_time":1.662322237},
{"learn":[25.2987296],"iteration":501,"passed_time":1.671538775,"remaining_time":1.658219741},
{"learn":[25.28528486],"iteration":502,"passed_time":1.674251357,"remaining_time":1.654280168},
{"learn":[25.27399125],"iteration":503,"passed_time":1.676761613,"remaining_time":1.650146349},
{"learn":[25.2629368],"iteration":504,"passed_time":1.679301456,"remaining_time":1.646047962},
{"learn":[25.25261957],"iteration":505,"passed_time":1.681903681,"remaining_time":1.642016637},
{"learn":[25.24385478],"iteration":506,"passed_time":1.684488919,"remaining_time":1.637974432},
{"learn":[25.2349335],"iteration":507,"passed_time":1.686997944,"remaining_time":1.63386415},
{"learn":[25.21577074],"iteration":508,"passed_time":1.689724289,"remaining_time":1.629969796},
{"learn":[25.20669821],"iteration":509,"passed_time":1.692367112,"remaining_time":1.625999774},
{"learn":[25.19916418],"iteration":510,"passed_time":1.695029742,"remaining_time":1.622053902},
{"learn":[25.18707432],"iteration":511,"passed_time":1.698191834,"remaining_time":1.618589092},
{"learn":[25.17848263],"iteration":512,"passed_time":1.701382789,"remaining_time":1.615152862},
{"learn":[25.16841909],"iteration":513,"passed_time":1.704449277,"remaining_time":1.6115999},
{"learn":[25.16023992],"iteration":514,"passed_time":1.707358244,"remaining_time":1.607900482},
{"learn":[25.14859857],"iteration":515,"passed_time":1.710738837,"remaining_time":1.604646506},
{"learn":[25.13670203],"iteration":516,"passed_time":1.713842975,"remaining_time":1.601133765},
{"learn":[25.12281212],"iteration":517,"passed_time":1.717037798,"remaining_time":1.597706986},
{"learn":[25.10726471],"iteration":518,"passed_time":1.720232912,"remaining_time":1.59428137},
{"learn":[25.096835],"iteration":519,"passed_time":1.724311299,"remaining_time":1.591671968},
{"learn":[25.08438394],"iteration":520,"passed_time":1.729897678,"remaining_time":1.590443354},
{"learn":[25.07403487],"iteration":521,"passed_time":1.733407294,"remaining_time":1.587296334},
{"learn":[25.06177004],"iteration":522,"passed_time":1.738839709,"remaining_time":1.585901609},
{"learn":[25.05427695],"iteration":523,"passed_time":1.741409348,"remaining_time":1.581890935},
{"learn":[25.04622826],"iteration":524,"passed_time":1.743985633,"remaining_time":1.577891763},
{"learn":[25.03154236],"iteration":525,"passed_time":1.746689358,"remaining_time":1.574012843},
{"learn":[25.01934486],"iteration":526,"passed_time":1.749327589,"remaining_time":1.570079601},
{"learn":[25.00994097],"iteration":527,"passed_time":1.751852494,"remaining_time":1.566049957},
{"learn":[25.0015619],"iteration":528,"passed_time":1.754399876,"remaining_time":1.562046014},
{"learn":[24.98996004],"iteration":529,"passed_time":1.757037309,"remaining_time":1.558127425},
{"learn":[24.98007777],"iteration":530,"passed_time":1.75959444,"remaining_time":1.554142735},
{"learn":[24.97030834],"iteration":531,"passed_time":1.762085432,"remaining_time":1.55010523},
{"learn":[24.95988934],"iteration":532,"passed_time":1.764610808,"remaining_time":1.546103654},
{"learn":[24.94916856],"iteration":533,"passed_time":1.767141087,"remaining_time":1.542111885},
{"learn":[24.93837279],"iteration":534,"passed_time":1.769773111,"remaining_time":1.538214012},
{"learn":[24.92669702],"iteration":535,"passed_time":1.772313665,"remaining_time":1.53424168},
{"learn":[24.91954431],"iteration":536,"passed_time":1.774845396,"remaining_time":1.530267073},
{"learn":[24.90900172],"iteration":537,"passed_time":1.777616434,"remaining_time":1.526503331},
{"learn":[24.89728506],"iteration":538,"passed_time":1.780760843,"remaining_time":1.523062613},
{"learn":[24.89195837],"iteration":539,"passed_time":1.783304088,"remaining_time":1.51911089},
{"learn":[24.88548741],"iteration":540,"passed_time":1.785953038,"remaining_time":1.515254056},
{"learn":[24.87268359],"iteration":541,"passed_time":1.788635115,"remaining_time":1.511429673},
{"learn":[24.85919305],"iteration":542,"passed_time":1.791237587,"remaining_time":1.507542499},
{"learn":[24.84969558],"iteration":543,"passed_time":1.794030978,"remaining_time":1.503820085},
{"learn":[24.83869082],"iteration":544,"passed_time":1.797314888,"remaining_time":1.500510594},
{"learn":[24.83042801],"iteration":545,"passed_time":1.800503438,"remaining_time":1.497121907},
{"learn":[24.81854128],"iteration":546,"passed_time":1.803608336,"remaining_time":1.493664673},
{"learn":[24.80996647],"iteration":547,"passed_time":1.806899275,"remaining_time":1.490362176},
{"learn":[24.80355585],"iteration":548,"passed_time":1.811605355,"remaining_time":1.48822225},
{"learn":[24.79391867],"iteration":549,"passed_time":1.818808751,"remaining_time":1.488116251},
{"learn":[24.7871818],"iteration":550,"passed_time":1.825338355,"remaining_time":1.487435429},
{"learn":[24.77680584],"iteration":551,"passed_time":1.828399706,"remaining_time":1.483918602},
{"learn":[24.76648277],"iteration":552,"passed_time":1.83136985,"remaining_time":1.480329698},
{"learn":[24.75828538],"iteration":553,"passed_time":1.834110586,"remaining_time":1.476558342},
{"learn":[24.74701753],"iteration":554,"passed_time":1.836689916,"remaining_time":1.472661284},
{"learn":[24.73757694],"iteration":555,"passed_time":1.839529,"remaining_time":1.468976396},
{"learn":[24.72969876],"iteration":556,"passed_time":1.842083691,"remaining_time":1.465068358},
{"learn":[24.71888505],"iteration":557,"passed_time":1.844682703,"remaining_time":1.461200277},
{"learn":[24.70995205],"iteration":558,"passed_time":1.847177009,"remaining_time":1.457254134},
{"learn":[24.69668298],"iteration":559,"passed_time":1.849965603,"remaining_time":1.453544403},
{"learn":[24.68495918],"iteration":560,"passed_time":1.852602173,"remaining_time":1.449718991},
{"learn":[24.67610322],"iteration":561,"passed_time":1.855249665,"remaining_time":1.445906323},
{"learn":[24.66728439],"iteration":562,"passed_time":1.857880375,"remaining_time":1.442084767},
{"learn":[24.6564928],"iteration":563,"passed_time":1.860547694,"remaining_time":1.438295735},
{"learn":[24.64463477],"iteration":564,"passed_time":1.863185959,"remaining_time":1.434488305},
{"learn":[24.63685296],"iteration":565,"passed_time":1.86574731,"remaining_time":1.430626029},
{"learn":[24.62333444],"iteration":566,"passed_time":1.868393239,"remaining_time":1.426832932},
{"learn":[24.6157089],"iteration":567,"passed_time":1.870993073,"remaining_time":1.423008816},
{"learn":[24.6100747],"iteration":568,"passed_time":1.873435998,"remaining_time":1.41907015},
{"learn":[24.59993782],"iteration":569,"passed_time":1.8760517,"remaining_time":1.415267072},
{"learn":[24.58710715],"iteration":570,"passed_time":1.878633317,"remaining_time":1.411442544},
{"learn":[24.57824114],"iteration":571,"passed_time":1.881104086,"remaining_time":1.407539421},
{"learn":[24.56845517],"iteration":572,"passed_time":1.883663928,"remaining_time":1.403707674},
{"learn":[24.56096707],"iteration":573,"passed_time":1.886225466,"remaining_time":1.399881618},
{"learn":[24.55309839],"iteration":574,"passed_time":1.888715235,"remaining_time":1.396006913},
{"learn":[24.54497721],"iteration":575,"passed_time":1.89135954,"remaining_time":1.392250772},
{"learn":[24.5343047],"iteration":576,"passed_time":1.894615343,"remaining_time":1.388946777},
{"learn":[24.52243709],"iteration":577,"passed_time":1.89789862,"remaining_time":1.385663006},
{"learn":[24.51352728],"iteration":578,"passed_time":1.902189162,"remaining_time":1.383111636},
{"learn":[24.5053783],"iteration":579,"passed_time":1.905380055,"remaining_time":1.379757971},
{"learn":[24.49842912],"iteration":580,"passed_time":1.908343951,"remaining_time":1.376241163},
{"learn":[24.49081974],"iteration":581,"passed_time":1.914717537,"remaining_time":1.375175138},
{"learn":[24.47965195],"iteration":582,"passed_time":1.920367879,"remaining_time":1.373573595},
{"learn":[24.46939155],"iteration":583,"passed_time":1.92420708,"remaining_time":1.370668057},
{"learn":[24.45968435],"iteration":584,"passed_time":1.927763798,"remaining_time":1.367558934},
{"learn":[24.4535473],"iteration":585,"passed_time":1.930680009,"remaining_time":1.363995774},
{"learn":[24.44155765],"iteration":586,"passed_time":1.933312484,"remaining_time":1.360235189},
{"learn":[24.43462107],"iteration":587,"passed_time":1.935863665,"remaining_time":1.356421479},
{"learn":[24.42429783],"iteration":588,"passed_time":1.938455075,"remaining_time":1.352640128},
{"learn":[24.41420277],"iteration":589,"passed_time":1.941094693,"remaining_time":1.348896312},
{"learn":[24.39761136],"iteration":590,"passed_time":1.943852397,"remaining_time":1.345237953},
{"learn":[24.39049917],"iteration":591,"passed_time":1.946469097,"remaining_time":1.341485459},
{"learn":[24.38054427],"iteration":592,"passed_time":1.949055374,"remaining_time":1.337715914},
{"learn":[24.37296459],"iteration":593,"passed_time":1.951617806,"remaining_time":1.333934056},
{"learn":[24.36553809],"iteration":594,"passed_time":1.954273451,"remaining_time":1.330219744},
{"learn":[24.35985117],"iteration":595,"passed_time":1.956837319,"remaining_time":1.326446773},
{"learn":[24.35018578],"iteration":596,"passed_time":1.959460794,"remaining_time":1.32271809},
{"learn":[24.34023472],"iteration":597,"passed_time":1.96204438,"remaining_time":1.318966289},
{"learn":[24.33322347],"iteration":598,"passed_time":1.964538426,"remaining_time":1.315158446},
{"learn":[24.32716214],"iteration":599,"passed_time":1.967067415,"remaining_time":1.311378277},
{"learn":[24.31514693],"iteration":600,"passed_time":1.969636557,"remaining_time":1.307628929},
{"learn":[24.30560643],"iteration":601,"passed_time":1.972245174,"remaining_time":1.3039096},
{"learn":[24.29703488],"iteration":602,"passed_time":1.974800488,"remaining_time":1.300158862},
{"learn":[24.28523384],"iteration":603,"passed_time":1.977397736,"remaining_time":1.296439575},
{"learn":[24.27502068],"iteration":604,"passed_time":1.9800432,"remaining_time":1.292755478},
{"learn":[24.26713348],"iteration":605,"passed_time":1.982632031,"remaining_time":1.289037987},
{"learn":[24.2511387],"iteration":606,"passed_time":1.9852884,"remaining_time":1.285367943},
{"learn":[24.24298048],"iteration":607,"passed_time":1.98782404,"remaining_time":1.281623394},
{"learn":[24.23555762],"iteration":608,"passed_time":1.990435665,"remaining_time":1.277931601},
{"learn":[24.22198888],"iteration":609,"passed_time":1.993621295,"remaining_time":1.274610336},
{"learn":[24.21092319],"iteration":610,"passed_time":1.997735943,"remaining_time":1.271880985},
{"learn":[24.199694],"iteration":611,"passed_time":2.001113092,"remaining_time":1.268679542},
{"learn":[24.1889387],"iteration":612,"passed_time":2.014192155,"remaining_time":1.271602551},
{"learn":[24.17914018],"iteration":613,"passed_time":2.017588983,"remaining_time":1.268386559},
{"learn":[24.17103373],"iteration":614,"passed_time":2.020566389,"remaining_time":1.264907414},
{"learn":[24.16128998],"iteration":615,"passed_time":2.023571225,"remaining_time":1.261446997},
{"learn":[24.15228593],"iteration":616,"passed_time":2.026575155,"remaining_time":1.257987495},
{"learn":[24.14423277],"iteration":617,"passed_time":2.029332897,"remaining_time":1.254377292},
{"learn":[24.13583108],"iteration":618,"passed_time":2.03190568,"remaining_time":1.250656},
{"learn":[24.13020034],"iteration":619,"passed_time":2.034503401,"remaining_time":1.246953698},
{"learn":[24.11947061],"iteration":620,"passed_time":2.037020133,"remaining_time":1.243205524},
{"learn":[24.11156481],"iteration":621,"passed_time":2.039570473,"remaining_time":1.239481735},
{"learn":[24.10429318],"iteration":622,"passed_time":2.042242567,"remaining_time":1.235835389},
{"learn":[24.09510147],"iteration":623,"passed_time":2.044765628,"remaining_time":1.232102366},
{"learn":[24.08843283],"iteration":624,"passed_time":2.047630075,"remaining_time":1.228578045},
{"learn":[24.07401655],"iteration":625,"passed_time":2.050206974,"remaining_time":1.224884039},
{"learn":[24.06505737],"iteration":626,"passed_time":2.052838567,"remaining_time":1.221226133},
{"learn":[24.05521862],"iteration":627,"passed_time":2.055521589,"remaining_time":1.217601961},
{"learn":[24.04598071],"iteration":628,"passed_time":2.058078468,"remaining_time":1.213906378},
{"learn":[24.03078618],"iteration":629,"passed_time":2.060765455,"remaining_time":1.210290823},
{"learn":[24.02554412],"iteration":630,"passed_time":2.063351307,"remaining_time":1.206619069},
{"learn":[24.01707036],"iteration":631,"passed_time":2.066182675,"remaining_time":1.20309371},
{"learn":[24.00770369],"iteration":632,"passed_time":2.068818443,"remaining_time":1.199457138},
{"learn":[23.99922189],"iteration":633,"passed_time":2.071535587,"remaining_time":1.195870702},
{"learn":[23.98714425],"iteration":634,"passed_time":2.074073816,"remaining_time":1.192184162},
{"learn":[23.97437192],"iteration":635,"passed_time":2.076709924,"remaining_time":1.188557252},
{"learn":[23.96342555],"iteration":636,"passed_time":2.079261666,"remaining_time":1.184885377},
{"learn":[23.9513683],"iteration":637,"passed_time":2.081894004,"remaining_time":1.181262742},
{"learn":[23.94117368],"iteration":638,"passed_time":2.084584913,"remaining_time":1.177676297},
{"learn":[23.92985727],"iteration":639,"passed_time":2.087181442,"remaining_time":1.174039561},
{"learn":[23.92113664],"iteration":640,"passed_time":2.090711032,"remaining_time":1.170928643},
{"learn":[23.91183335],"iteration":641,"passed_time":2.101432208,"remaining_time":1.171826683},
{"learn":[23.90415107],"iteration":642,"passed_time":2.109581149,"remaining_time":1.171260451},
{"learn":[23.89332085],"iteration":643,"passed_time":2.113132994,"remaining_time":1.168129419},
{"learn":[23.87807038],"iteration":644,"passed_time":2.116539779,"remaining_time":1.164917243},
{"learn":[23.87096258],"iteration":645,"passed_time":2.119544649,"remaining_time":1.16148422},
{"learn":[23.86211106],"iteration":646,"passed_time":2.122545847,"remaining_time":1.158050516},
{"learn":[23.85703204],"iteration":647,"passed_time":2.125537227,"remaining_time":1.154612815},
{"learn":[23.84936784],"iteration":648,"passed_time":2.128375068,"remaining_time":1.15109345},
{"learn":[23.84465139],"iteration":649,"passed_time":2.130880058,"remaining_time":1.147396955},
{"learn":[23.83540946],"iteration":650,"passed_time":2.133255321,"remaining_time":1.143634573},
{"learn":[23.82505353],"iteration":651,"passed_time":2.135943071,"remaining_time":1.140043234},
{"learn":[23.81628777],"iteration":652,"passed_time":2.138657038,"remaining_time":1.136468594},
{"learn":[23.8107478],"iteration":653,"passed_time":2.141173187,"remaining_time":1.132791931},
{"learn":[23.80491234],"iteration":654,"passed_time":2.143682745,"remaining_time":1.129115339},
{"learn":[23.79489835],"iteration":655,"passed_time":2.146314451,"remaining_time":1.125506359},
{"learn":[23.78649623],"iteration":656,"passed_time":2.148888228,"remaining_time":1.12187011},
{"learn":[23.77753115],"iteration":657,"passed_time":2.151555799,"remaining_time":1.118285841},
{"learn":[23.76546269],"iteration":658,"passed_time":2.154244104,"remaining_time":1.114715082},
{"learn":[23.75814511],"iteration":659,"passed_time":2.156743235,"remaining_time":1.111049545},
{"learn":[23.75112166],"iteration":660,"passed_time":2.159353192,"remaining_time":1.107444375},
{"learn":[23.7386882],"iteration":661,"passed_time":2.162056178,"remaining_time":1.10388971},
{"learn":[23.72843121],"iteration":662,"passed_time":2.164658424,"remaining_time":1.100286409},
{"learn":[23.72076554],"iteration":663,"passed_time":2.167222645,"remaining_time":1.096666881},
{"learn":[23.71382785],"iteration":664,"passed_time":2.169996538,"remaining_time":1.093156151},
{"learn":[23.70356174],"iteration":665,"passed_time":2.172722927,"remaining_time":1.08962381},
{"learn":[23.6942529],"iteration":666,"passed_time":2.175337072,"remaining_time":1.086037848},
{"learn":[23.68888407],"iteration":667,"passed_time":2.177862261,"remaining_time":1.082410585},
{"learn":[23.67957958],"iteration":668,"passed_time":2.180451817,"remaining_time":1.078818462},
{"learn":[23.6739075],"iteration":669,"passed_time":2.183081121,"remaining_time":1.07524891},
{"learn":[23.66703515],"iteration":670,"passed_time":2.185641512,"remaining_time":1.071648372},
{"learn":[23.65657493],"iteration":671,"passed_time":2.190299311,"remaining_time":1.069074664},
{"learn":[23.65021781],"iteration":672,"passed_time":2.198600224,"remaining_time":1.068264893},
{"learn":[23.636307],"iteration":673,"passed_time":2.203821483,"remaining_time":1.065943329},
{"learn":[23.63003504],"iteration":674,"passed_time":2.208052933,"remaining_time":1.063136597},
{"learn":[23.62386639],"iteration":675,"passed_time":2.211183563,"remaining_time":1.059798039},
{"learn":[23.61701198],"iteration":676,"passed_time":2.215079424,"remaining_time":1.056825191},
{"learn":[23.61044305],"iteration":677,"passed_time":2.218101439,"remaining_time":1.053434607},
{"learn":[23.60223435],"iteration":678,"passed_time":2.221967766,"remaining_time":1.050444261},
{"learn":[23.59400969],"iteration":679,"passed_time":2.224907539,"remaining_time":1.047015313},
{"learn":[23.58587699],"iteration":680,"passed_time":2.227610865,"remaining_time":1.043477042},
{"learn":[23.58016312],"iteration":681,"passed_time":2.233697413,"remaining_time":1.041518735},
{"learn":[23.57027463],"iteration":682,"passed_time":2.23633267,"remaining_time":1.037946495},
{"learn":[23.56166477],"iteration":683,"passed_time":2.238830533,"remaining_time":1.034313521},
{"learn":[23.55423993],"iteration":684,"passed_time":2.241405922,"remaining_time":1.030719512},
{"learn":[23.54282775],"iteration":685,"passed_time":2.244100773,"remaining_time":1.027183153},
{"learn":[23.53413519],"iteration":686,"passed_time":2.246747576,"remaining_time":1.023627353},
{"learn":[23.52594017],"iteration":687,"passed_time":2.249290077,"remaining_time":1.020026895},
{"learn":[23.52116558],"iteration":688,"passed_time":2.251764678,"remaining_time":1.01639886},
{"learn":[23.51301078],"iteration":689,"passed_time":2.254442268,"remaining_time":1.012865367},
{"learn":[23.50476345],"iteration":690,"passed_time":2.257058826,"remaining_time":1.009307058},
{"learn":[23.49287683],"iteration":691,"passed_time":2.259762041,"remaining_time":1.005790042},
{"learn":[23.48581123],"iteration":692,"passed_time":2.262289916,"remaining_time":1.002197697},
{"learn":[23.47737267],"iteration":693,"passed_time":2.264905445,"remaining_time":0.9986470692},
{"learn":[23.46153971],"iteration":694,"passed_time":2.26747208,"remaining_time":0.9950776753},
{"learn":[23.45291116],"iteration":695,"passed_time":2.270029099,"remaining_time":0.9915069626},
{"learn":[23.44526367],"iteration":696,"passed_time":2.272665811,"remaining_time":0.9879738031},
{"learn":[23.43860036],"iteration":697,"passed_time":2.275132165,"remaining_time":0.9843695041},
{"learn":[23.42774884],"iteration":698,"passed_time":2.277763573,"remaining_time":0.9808395356},
{"learn":[23.42050025],"iteration":699,"passed_time":2.280284955,"remaining_time":0.9772649807},
{"learn":[23.41489407],"iteration":700,"passed_time":2.282801414,"remaining_time":0.9736913306},
{"learn":[23.40442178],"iteration":701,"passed_time":2.285467932,"remaining_time":0.9701843927},
{"learn":[23.39355886],"iteration":702,"passed_time":2.28883268,"remaining_time":0.9669748308},
{"learn":[23.38520525],"iteration":703,"passed_time":2.293647719,"remaining_time":0.9643746093},
{"learn":[23.37592922],"iteration":704,"passed_time":2.296953576,"remaining_time":0.9611366026},
{"learn":[23.37064017],"iteration":705,"passed_time":2.300602922,"remaining_time":0.9580414434},
{"learn":[23.3618049],"iteration":706,"passed_time":2.306276712,"remaining_time":0.9557837009},
{"learn":[23.3516125],"iteration":707,"passed_time":2.311905285,"remaining_time":0.9534976601},
{"learn":[23.34170798],"iteration":708,"passed_time":2.315513503,"remaining_time":0.950372961},
{"learn":[23.33645005],"iteration":709,"passed_time":2.321402211,"remaining_time":0.9481783677},
{"learn":[23.32691154],"iteration":710,"passed_time":2.324379693,"remaining_time":0.9447900581},
{"learn":[23.31904671],"iteration":711,"passed_time":2.32700909,"remaining_time":0.9412621039},
{"learn":[23.31098936],"iteration":712,"passed_time":2.329712474,"remaining_time":0.9377664516},
{"learn":[23.30228727],"iteration":713,"passed_time":2.332298088,"remaining_time":0.9342258446},
{"learn":[23.29367613],"iteration":714,"passed_time":2.334834341,"remaining_time":0.930668234},
{"learn":[23.28771932],"iteration":715,"passed_time":2.337411692,"remaining_time":0.9271297772},
{"learn":[23.28041014],"iteration":716,"passed_time":2.339982921,"remaining_time":0.9235915855},
{"learn":[23.2754553],"iteration":717,"passed_time":2.342574706,"remaining_time":0.9200641603},
{"learn":[23.2658642],"iteration":718,"passed_time":2.345213549,"remaining_time":0.9165577291},
{"learn":[23.25868634],"iteration":719,"passed_time":2.347775803,"remaining_time":0.9130239234},
{"learn":[23.24773221],"iteration":720,"passed_time":2.350431876,"remaining_time":0.9095291171},
{"learn":[23.2397581],"iteration":721,"passed_time":2.353039787,"remaining_time":0.9060180898},
{"learn":[23.23224613],"iteration":722,"passed_time":2.35560414,"remaining_time":0.9024928724},
{"learn":[23.22231595],"iteration":723,"passed_time":2.358162394,"remaining_time":0.8989679844},
{"learn":[23.21233322],"iteration":724,"passed_time":2.360852095,"remaining_time":0.8954956221},
{"learn":[23.20547634],"iteration":725,"passed_time":2.363355749,"remaining_time":0.8919551999},
{"learn":[23.19815108],"iteration":726,"passed_time":2.365926034,"remaining_time":0.8884426511},
{"learn":[23.19165553],"iteration":727,"passed_time":2.368501655,"remaining_time":0.8849346843},
{"learn":[23.1862273],"iteration":728,"passed_time":2.371032623,"remaining_time":0.8814126761},
{"learn":[23.17876888],"iteration":729,"passed_time":2.373583045,"remaining_time":0.8779005783},
{"learn":[23.17167156],"iteration":730,"passed_time":2.37612862,"remaining_time":0.8743893279},
{"learn":[23.16406975],"iteration":731,"passed_time":2.378888788,"remaining_time":0.8709592829},
{"learn":[23.15639054],"iteration":732,"passed_time":2.381462591,"remaining_time":0.8674631811},
{"learn":[23.14895093],"iteration":733,"passed_time":2.384002258,"remaining_time":0.8639572216},
{"learn":[23.1389619],"iteration":734,"passed_time":2.388830703,"remaining_time":0.8612790971},
{"learn":[23.12977862],"iteration":735,"passed_time":2.397220315,"remaining_time":0.8598725043},
{"learn":[23.12072703],"iteration":736,"passed_time":2.410168716,"remaining_time":0.8600737752},
{"learn":[23.11093349],"iteration":737,"passed_time":2.420809374,"remaining_time":0.85942013},
{"learn":[23.10216972],"iteration":738,"passed_time":2.423900813,"remaining_time":0.8560732235},
{"learn":[23.09396157],"iteration":739,"passed_time":2.426778447,"remaining_time":0.8526518868},
{"learn":[23.0879689],"iteration":740,"passed_time":2.430403099,"remaining_time":0.849493121},
{"learn":[23.0802961],"iteration":741,"passed_time":2.433001551,"remaining_time":0.8459762805},
{"learn":[23.07089123],"iteration":742,"passed_time":2.435663988,"remaining_time":0.8424840443},
{"learn":[23.06258912],"iteration":743,"passed_time":2.438335446,"remaining_time":0.8389971427},
{"learn":[23.05611547],"iteration":744,"passed_time":2.440878738,"remaining_time":0.8354685614},
{"learn":[23.04837053],"iteration":745,"passed_time":2.443399933,"remaining_time":0.8319350979},
{"learn":[23.03750477],"iteration":746,"passed_time":2.445934481,"remaining_time":0.8284088669},
{"learn":[23.03260945],"iteration":747,"passed_time":2.448458416,"remaining_time":0.8248817122},
{"learn":[23.02477056],"iteration":748,"passed_time":2.450993536,"remaining_time":0.8213609846},
{"learn":[23.02070869],"iteration":749,"passed_time":2.453507611,"remaining_time":0.8178358702},
{"learn":[23.01355763],"iteration":750,"passed_time":2.456015902,"remaining_time":0.8143115308},
{"learn":[23.00577971],"iteration":751,"passed_time":2.458612188,"remaining_time":0.8108189131},
{"learn":[22.99853981],"iteration":752,"passed_time":2.461291971,"remaining_time":0.8073560649},
{"learn":[22.98864673],"iteration":753,"passed_time":2.463899929,"remaining_time":0.80387186},
{"learn":[22.98221182],"iteration":754,"passed_time":2.46642874,"remaining_time":0.8003642931},
{"learn":[22.97236863],"iteration":755,"passed_time":2.469089134,"remaining_time":0.7969017841},
{"learn":[22.96726207],"iteration":756,"passed_time":2.471607664,"remaining_time":0.7933958551},
{"learn":[22.96045051],"iteration":757,"passed_time":2.474214814,"remaining_time":0.7899208246},
{"learn":[22.95268328],"iteration":758,"passed_time":2.476590026,"remaining_time":0.7863744352},
{"learn":[22.93886641],"iteration":759,"passed_time":2.4791873,"remaining_time":0.7829012525},
{"learn":[22.92990057],"iteration":760,"passed_time":2.481794455,"remaining_time":0.7794334753},
{"learn":[22.92558129],"iteration":761,"passed_time":2.485125977,"remaining_time":0.7761942028},
{"learn":[22.91391957],"iteration":762,"passed_time":2.490479649,"remaining_time":0.7735828004},
{"learn":[22.90785122],"iteration":763,"passed_time":2.493764934,"remaining_time":0.7703252937},
{"learn":[22.89613906],"iteration":764,"passed_time":2.496365115,"remaining_time":0.7668572577},
{"learn":[22.88643321],"iteration":765,"passed_time":2.499119011,"remaining_time":0.7634384446},
{"learn":[22.87741294],"iteration":766,"passed_time":2.501731581,"remaining_time":0.7599784335},
{"learn":[22.86914285],"iteration":767,"passed_time":2.504331477,"remaining_time":0.7565168004},
{"learn":[22.85656285],"iteration":768,"passed_time":2.507045739,"remaining_time":0.753091763},
{"learn":[22.84391431],"iteration":769,"passed_time":2.509853146,"remaining_time":0.7496963941},
{"learn":[22.83966399],"iteration":770,"passed_time":2.51241866,"remaining_time":0.7462307044},
{"learn":[22.83255011],"iteration":771,"passed_time":2.515118095,"remaining_time":0.7428068986},
{"learn":[22.82703974],"iteration":772,"passed_time":2.517711229,"remaining_time":0.7393537504},
{"learn":[22.81929483],"iteration":773,"passed_time":2.520295085,"remaining_time":0.7359001152},
{"learn":[22.8138306],"iteration":774,"passed_time":2.522906416,"remaining_time":0.7324567014},
{"learn":[22.80659423],"iteration":775,"passed_time":2.525553618,"remaining_time":0.7290257867},
{"learn":[22.79587068],"iteration":776,"passed_time":2.528182144,"remaining_time":0.7255915292},
{"learn":[22.78939087],"iteration":777,"passed_time":2.530920829,"remaining_time":0.7221907765},
{"learn":[22.78392699],"iteration":778,"passed_time":2.533451388,"remaining_time":0.7187326786},
{"learn":[22.77950737],"iteration":779,"passed_time":2.536077709,"remaining_time":0.7153039691},
{"learn":[22.77053477],"iteration":780,"passed_time":2.538694417,"remaining_time":0.7118746188},
{"learn":[22.75822068],"iteration":781,"passed_time":2.5413596,"remaining_time":0.7084608604},
{"learn":[22.74811201],"iteration":782,"passed_time":2.544035223,"remaining_time":0.7050519073},
{"learn":[22.74290679],"iteration":783,"passed_time":2.546581822,"remaining_time":0.7016092775},
{"learn":[22.73598276],"iteration":784,"passed_time":2.549133346,"remaining_time":0.6981702796},
{"learn":[22.72780892],"iteration":785,"passed_time":2.551868211,"remaining_time":0.694783457},
{"learn":[22.72058953],"iteration":786,"passed_time":2.554422068,"remaining_time":0.6913493019},
{"learn":[22.71591168],"iteration":787,"passed_time":2.556957859,"remaining_time":0.6879125204},
{"learn":[22.70612541],"iteration":788,"passed_time":2.559665488,"remaining_time":0.6845239772},
{"learn":[22.69678272],"iteration":789,"passed_time":2.562321959,"remaining_time":0.6811235586},
{"learn":[22.69039054],"iteration":790,"passed_time":2.564984231,"remaining_time":0.677726554},
{"learn":[22.68583781],"iteration":791,"passed_time":2.567586982,"remaining_time":0.674315773},
{"learn":[22.67258232],"iteration":792,"passed_time":2.57030672,"remaining_time":0.6709375675},
{"learn":[22.66808243],"iteration":793,"passed_time":2.572837429,"remaining_time":0.6675119778},
{"learn":[22.65670062],"iteration":794,"passed_time":2.575501925,"remaining_time":0.6641231379},
{"learn":[22.64858535],"iteration":795,"passed_time":2.578108383,"remaining_time":0.660721244},
{"learn":[22.64299969],"iteration":796,"passed_time":2.580763147,"remaining_time":0.6573336499},
{"learn":[22.63822545],"iteration":797,"passed_time":2.583413291,"remaining_time":0.6539467227},
{"learn":[22.62728631],"iteration":798,"passed_time":2.585984419,"remaining_time":0.6505417626},
{"learn":[22.61881949],"iteration":799,"passed_time":2.588547748,"remaining_time":0.647136937},
{"learn":[22.61348414],"iteration":800,"passed_time":2.591164064,"remaining_time":0.6437473768},
{"learn":[22.60278749],"iteration":801,"passed_time":2.593748718,"remaining_time":0.6403519279},
{"learn":[22.59669282],"iteration":802,"passed_time":2.596378973,"remaining_time":0.6369696858},
{"learn":[22.58889299],"iteration":803,"passed_time":2.598974593,"remaining_time":0.6335808708},
{"learn":[22.58321214],"iteration":804,"passed_time":2.601574664,"remaining_time":0.630195105},
{"learn":[22.57554392],"iteration":805,"passed_time":2.604168622,"remaining_time":0.6268098171},
{"learn":[22.56990605],"iteration":806,"passed_time":2.606714514,"remaining_time":0.6234149953},
{"learn":[22.55782417],"iteration":807,"passed_time":2.60947388,"remaining_time":0.6200730012},
{"learn":[22.55279435],"iteration":808,"passed_time":2.612057956,"remaining_time":0.6166910626},
{"learn":[22.54749566],"iteration":809,"passed_time":2.614659334,"remaining_time":0.6133151524},
{"learn":[22.54111084],"iteration":810,"passed_time":2.617253863,"remaining_time":0.6099395563},
{"learn":[22.53167586],"iteration":811,"passed_time":2.619869509,"remaining_time":0.606570773},
{"learn":[22.52533317],"iteration":812,"passed_time":2.622491057,"remaining_time":0.6032052001},
{"learn":[22.51834806],"iteration":813,"passed_time":2.625036432,"remaining_time":0.5998240497},
{"learn":[22.5068085],"iteration":814,"passed_time":2.627735997,"remaining_time":0.5964799502},
{"learn":[22.49800149],"iteration":815,"passed_time":2.630240022,"remaining_time":0.5930933382},
{"learn":[22.49109128],"iteration":816,"passed_time":2.632946639,"remaining_time":0.5897542655},
{"learn":[22.48418179],"iteration":817,"passed_time":2.635537094,"remaining_time":0.5863908937},
{"learn":[22.472228],"iteration":818,"passed_time":2.638242375,"remaining_time":0.5830547861},
{"learn":[22.46482773],"iteration":819,"passed_time":2.640750244,"remaining_time":0.5796768828},
{"learn":[22.45566593],"iteration":820,"passed_time":2.643334825,"remaining_time":0.5763178242},
{"learn":[22.4509482],"iteration":821,"passed_time":2.645843601,"remaining_time":0.5729442348},
{"learn":[22.44474641],"iteration":822,"passed_time":2.648342442,"remaining_time":0.5695706103},
{"learn":[22.43853722],"iteration":823,"passed_time":2.650839804,"remaining_time":0.5661987931},
{"learn":[22.42602307],"iteration":824,"passed_time":2.653410477,"remaining_time":0.5628446466},
{"learn":[22.41966196],"iteration":825,"passed_time":2.656072202,"remaining_time":0.5595115776},
{"learn":[22.41348663],"iteration":826,"passed_time":2.658784133,"remaining_time":0.5561906348},
{"learn":[22.40709062],"iteration":827,"passed_time":2.661311372,"remaining_time":0.552832797},
{"learn":[22.39783813],"iteration":828,"passed_time":2.663977976,"remaining_time":0.5495057104},
{"learn":[22.39293213],"iteration":829,"passed_time":2.66655394,"remaining_time":0.5461616504},
{"learn":[22.38194941],"iteration":830,"passed_time":2.669332742,"remaining_time":0.54286069},
{"learn":[22.37845871],"iteration":831,"passed_time":2.671802417,"remaining_time":0.5394985649},
{"learn":[22.37165846],"iteration":832,"passed_time":2.674476856,"remaining_time":0.5361796339},
{"learn":[22.36577755],"iteration":833,"passed_time":2.677044409,"remaining_time":0.5328409735},
{"learn":[22.3582767],"iteration":834,"passed_time":2.679639018,"remaining_time":0.5295095065},
{"learn":[22.35163109],"iteration":835,"passed_time":2.682171957,"remaining_time":0.5261677045},
{"learn":[22.34439637],"iteration":836,"passed_time":2.684795318,"remaining_time":0.5228454442},
{"learn":[22.33449356],"iteration":837,"passed_time":2.687387231,"remaining_time":0.5195187726},
{"learn":[22.32766704],"iteration":838,"passed_time":2.689983244,"remaining_time":0.5161946391},
{"learn":[22.32246713],"iteration":839,"passed_time":2.692482209,"remaining_time":0.5128537542},
{"learn":[22.31995822],"iteration":840,"passed_time":2.694921257,"remaining_time":0.5095035433},
{"learn":[22.31069637],"iteration":841,"passed_time":2.697599839,"remaining_time":0.5062004448},
{"learn":[22.30599949],"iteration":842,"passed_time":2.700144224,"remaining_time":0.5028738352},
{"learn":[22.29953323],"iteration":843,"passed_time":2.702672969,"remaining_time":0.4995461886},
{"learn":[22.29298481],"iteration":844,"passed_time":2.705312163,"remaining_time":0.4962406927},
{"learn":[22.28691517],"iteration":845,"passed_time":2.70795311,"remaining_time":0.4929370909},
{"learn":[22.28258175],"iteration":846,"passed_time":2.710541127,"remaining_time":0.4896254928},
{"learn":[22.27121432],"iteration":847,"passed_time":2.713183905,"remaining_time":0.4863254169},
{"learn":[22.26222995],"iteration":848,"passed_time":2.715820237,"remaining_time":0.4830257431},
{"learn":[22.25258217],"iteration":849,"passed_time":2.718525561,"remaining_time":0.4797398049},
{"learn":[22.24571959],"iteration":850,"passed_time":2.721170122,"remaining_time":0.4764445924},
{"learn":[22.23510811],"iteration":851,"passed_time":2.723686973,"remaining_time":0.4731287231},
{"learn":[22.22992428],"iteration":852,"passed_time":2.7263762,"remaining_time":0.469844433},
{"learn":[22.22147266],"iteration":853,"passed_time":2.729221236,"remaining_time":0.4665881739},
{"learn":[22.2180487],"iteration":854,"passed_time":2.731724518,"remaining_time":0.4632749183},
{"learn":[22.20961503],"iteration":855,"passed_time":2.734359951,"remaining_time":0.4599857862},
{"learn":[22.20188505],"iteration":856,"passed_time":2.736981187,"remaining_time":0.4566958106},
{"learn":[22.19470766],"iteration":857,"passed_time":2.739647391,"remaining_time":0.4534148363},
{"learn":[22.19011861],"iteration":858,"passed_time":2.742130056,"remaining_time":0.4501051663},
{"learn":[22.18579918],"iteration":859,"passed_time":2.744766333,"remaining_time":0.4468224263},
{"learn":[22.17889419],"iteration":860,"passed_time":2.747328831,"remaining_time":0.4435292771},
{"learn":[22.17139665],"iteration":861,"passed_time":2.750288951,"remaining_time":0.4403014794},
{"learn":[22.16314688],"iteration":862,"passed_time":2.75290551,"remaining_time":0.4370197623},
{"learn":[22.15683256],"iteration":863,"passed_time":2.75552235,"remaining_time":0.4337396291},
{"learn":[22.14908409],"iteration":864,"passed_time":2.758252135,"remaining_time":0.430478657},
{"learn":[22.14264161],"iteration":865,"passed_time":2.764058269,"remaining_time":0.4276949284},
{"learn":[22.13728882],"iteration":866,"passed_time":2.766731682,"remaining_time":0.4244236605},
{"learn":[22.12730501],"iteration":867,"passed_time":2.769436017,"remaining_time":0.4211584727},
{"learn":[22.12097436],"iteration":868,"passed_time":2.772046906,"remaining_time":0.4178804887},
{"learn":[22.11681621],"iteration":869,"passed_time":2.774803168,"remaining_time":0.4146257608},
{"learn":[22.10779472],"iteration":870,"passed_time":2.77745465,"remaining_time":0.4113566588},
{"learn":[22.1018507],"iteration":871,"passed_time":2.780000516,"remaining_time":0.4080734702},
{"learn":[22.09384838],"iteration":872,"passed_time":2.782634962,"remaining_time":0.404804857},
{"learn":[22.09000655],"iteration":873,"passed_time":2.785440043,"remaining_time":0.4015622946},
{"learn":[22.0835447],"iteration":874,"passed_time":2.788643845,"remaining_time":0.3983776921},
{"learn":[22.08048535],"iteration":875,"passed_time":2.791765532,"remaining_time":0.3951814223},
{"learn":[22.07501181],"iteration":876,"passed_time":2.795362942,"remaining_time":0.3920520431},
{"learn":[22.06694466],"iteration":877,"passed_time":2.798566393,"remaining_time":0.3888668565},
{"learn":[22.06241108],"iteration":878,"passed_time":2.801734474,"remaining_time":0.3856767592},
{"learn":[22.05703899],"iteration":879,"passed_time":2.809279513,"remaining_time":0.38308357},
{"learn":[22.05342962],"iteration":880,"passed_time":2.818454377,"remaining_time":0.3806992859},
{"learn":[22.04324003],"iteration":881,"passed_time":2.827278992,"remaining_time":0.3782527449},
{"learn":[22.03214384],"iteration":882,"passed_time":2.830699366,"remaining_time":0.3750756805},
{"learn":[22.0287112],"iteration":883,"passed_time":2.833471756,"remaining_time":0.3718130358},
{"learn":[22.02090402],"iteration":884,"passed_time":2.837308098,"remaining_time":0.3686897528},
{"learn":[22.01171237],"iteration":885,"passed_time":2.839941998,"remaining_time":0.3654101443},
{"learn":[22.00219213],"iteration":886,"passed_time":2.842811131,"remaining_time":0.3621619592},
{"learn":[21.99333169],"iteration":887,"passed_time":2.845470444,"remaining_time":0.3588881642},
{"learn":[21.9871483],"iteration":888,"passed_time":2.848086729,"remaining_time":0.355610379},
{"learn":[21.97974285],"iteration":889,"passed_time":2.850701724,"remaining_time":0.3523339209},
{"learn":[21.97453152],"iteration":890,"passed_time":2.853094544,"remaining_time":0.349031768},
{"learn":[21.96737759],"iteration":891,"passed_time":2.855753642,"remaining_time":0.3457638939},
{"learn":[21.95706631],"iteration":892,"passed_time":2.858487911,"remaining_time":0.3425063902},
{"learn":[21.95118469],"iteration":893,"passed_time":2.861126123,"remaining_time":0.3392386678},
{"learn":[21.94471181],"iteration":894,"passed_time":2.863893731,"remaining_time":0.3359875326},
{"learn":[21.93904556],"iteration":895,"passed_time":2.866468006,"remaining_time":0.3327150364},
{"learn":[21.93231102],"iteration":896,"passed_time":2.869085856,"remaining_time":0.3294491005},
{"learn":[21.92566679],"iteration":897,"passed_time":2.871745501,"remaining_time":0.3261893554},
{"learn":[21.91937457],"iteration":898,"passed_time":2.874411086,"remaining_time":0.3229316126},
{"learn":[21.91137889],"iteration":899,"passed_time":2.877223695,"remaining_time":0.3196915216},
{"learn":[21.90173642],"iteration":900,"passed_time":2.8835516,"remaining_time":0.316838633},
{"learn":[21.89242412],"iteration":901,"passed_time":2.890637888,"remaining_time":0.3140604357},
{"learn":[21.88511873],"iteration":902,"passed_time":2.896394092,"remaining_time":0.3111298194},
{"learn":[21.87409738],"iteration":903,"passed_time":2.901670134,"remaining_time":0.3081419612},
{"learn":[21.86644506],"iteration":904,"passed_time":2.908325463,"remaining_time":0.3052938331},
{"learn":[21.86050295],"iteration":905,"passed_time":2.914549647,"remaining_time":0.3023925682},
{"learn":[21.85170652],"iteration":906,"passed_time":2.919013644,"remaining_time":0.2993034939},
{"learn":[21.84291659],"iteration":907,"passed_time":2.921607891,"remaining_time":0.2960219449},
{"learn":[21.8312172],"iteration":908,"passed_time":2.924230824,"remaining_time":0.2927447799},
{"learn":[21.82316279],"iteration":909,"passed_time":2.926897201,"remaining_time":0.2894733495},
{"learn":[21.81511324],"iteration":910,"passed_time":2.929468706,"remaining_time":0.286193979},
{"learn":[21.80771899],"iteration":911,"passed_time":2.932153164,"remaining_time":0.2829270597},
{"learn":[21.803743],"iteration":912,"passed_time":2.934640892,"remaining_time":0.2796426699},
{"learn":[21.79867414],"iteration":913,"passed_time":2.937233874,"remaining_time":0.2763699268},
{"learn":[21.78985685],"iteration":914,"passed_time":2.939849467,"remaining_time":0.2731007702},
{"learn":[21.78163163],"iteration":915,"passed_time":2.942582942,"remaining_time":0.2698438506},
{"learn":[21.77694752],"iteration":916,"passed_time":2.945360629,"remaining_time":0.2665920744},
{"learn":[21.76790207],"iteration":917,"passed_time":2.948251613,"remaining_time":0.2633514513},
{"learn":[21.7601708],"iteration":918,"passed_time":2.95104033,"remaining_time":0.2601025753},
{"learn":[21.75081033],"iteration":919,"passed_time":2.953885725,"remaining_time":0.2568596282},
{"learn":[21.74769507],"iteration":920,"passed_time":2.956726003,"remaining_time":0.2536171056},
{"learn":[21.73869301],"iteration":921,"passed_time":2.959623312,"remaining_time":0.2503802802},
{"learn":[21.73334944],"iteration":922,"passed_time":2.962428194,"remaining_time":0.2471364799},
{"learn":[21.72533136],"iteration":923,"passed_time":2.965307417,"remaining_time":0.2438997442},
{"learn":[21.72011946],"iteration":924,"passed_time":2.968107465,"remaining_time":0.2406573621},
{"learn":[21.71579894],"iteration":925,"passed_time":2.970960763,"remaining_time":0.2374201906},
{"learn":[21.70810663],"iteration":926,"passed_time":2.973892908,"remaining_time":0.2341900564},
{"learn":[21.70045887],"iteration":927,"passed_time":2.97787194,"remaining_time":0.2310417884},
{"learn":[21.69306325],"iteration":928,"passed_time":2.983398087,"remaining_time":0.2280099722},
{"learn":[21.68683683],"iteration":929,"passed_time":2.988951367,"remaining_time":0.2249748341},
{"learn":[21.68068006],"iteration":930,"passed_time":2.995738897,"remaining_time":0.2220257614},
{"learn":[21.67595986],"iteration":931,"passed_time":3.000831737,"remaining_time":0.2189448049},
{"learn":[21.67010967],"iteration":932,"passed_time":3.005296106,"remaining_time":0.2158144042},
{"learn":[21.65982218],"iteration":933,"passed_time":3.009698393,"remaining_time":0.2126767601},
{"learn":[21.6501401],"iteration":934,"passed_time":3.014009526,"remaining_time":0.209530074},
{"learn":[21.64436946],"iteration":935,"passed_time":3.017064285,"remaining_time":0.2062949938},
{"learn":[21.63678224],"iteration":936,"passed_time":3.019968487,"remaining_time":0.2030501758},
{"learn":[21.63183201],"iteration":937,"passed_time":3.022733571,"remaining_time":0.1997968885},
{"learn":[21.62607785],"iteration":938,"passed_time":3.025791129,"remaining_time":0.1965636409},
{"learn":[21.62335091],"iteration":939,"passed_time":3.02838861,"remaining_time":0.1933014006},
{"learn":[21.61476647],"iteration":940,"passed_time":3.031054124,"remaining_time":0.1900448388},
{"learn":[21.60436374],"iteration":941,"passed_time":3.033617116,"remaining_time":0.1867832194},
{"learn":[21.59663846],"iteration":942,"passed_time":3.037530275,"remaining_time":0.1836046932},
{"learn":[21.59152764],"iteration":943,"passed_time":3.040131991,"remaining_time":0.180346813},
{"learn":[21.58228405],"iteration":944,"passed_time":3.042771966,"remaining_time":0.1770925483},
{"learn":[21.57562166],"iteration":945,"passed_time":3.045460068,"remaining_time":0.1738423295},
{"learn":[21.56882628],"iteration":946,"passed_time":3.048002929,"remaining_time":0.1705851692},
{"learn":[21.56125923],"iteration":947,"passed_time":3.050795614,"remaining_time":0.1673432193},
{"learn":[21.5566713],"iteration":948,"passed_time":3.053435483,"remaining_time":0.1640940038},
{"learn":[21.55043107],"iteration":949,"passed_time":3.05599409,"remaining_time":0.1608417942},
{"learn":[21.54483902],"iteration":950,"passed_time":3.058932658,"remaining_time":0.1576106207},
{"learn":[21.5345735],"iteration":951,"passed_time":3.062847704,"remaining_time":0.154429296},
{"learn":[21.52780607],"iteration":952,"passed_time":3.065510731,"remaining_time":0.1511846845},
{"learn":[21.51929204],"iteration":953,"passed_time":3.068162476,"remaining_time":0.1479407483},
{"learn":[21.51046153],"iteration":954,"passed_time":3.070864395,"remaining_time":0.1447004165},
{"learn":[21.50167591],"iteration":955,"passed_time":3.073470524,"remaining_time":0.1414568024},
{"learn":[21.49569541],"iteration":956,"passed_time":3.076521091,"remaining_time":0.13823449},
{"learn":[21.48657519],"iteration":957,"passed_time":3.079575593,"remaining_time":0.1350127087},
{"learn":[21.48137752],"iteration":958,"passed_time":3.083093033,"remaining_time":0.1318110682},
{"learn":[21.47798161],"iteration":959,"passed_time":3.086840861,"remaining_time":0.1286183692},
{"learn":[21.47143558],"iteration":960,"passed_time":3.090679436,"remaining_time":0.1254281977},
{"learn":[21.46232689],"iteration":961,"passed_time":3.096908991,"remaining_time":0.1223311244},
{"learn":[21.45394554],"iteration":962,"passed_time":3.099532408,"remaining_time":0.1190889918},
{"learn":[21.45080018],"iteration":963,"passed_time":3.10205339,"remaining_time":0.1158443175},
{"learn":[21.44366706],"iteration":964,"passed_time":3.104599864,"remaining_time":0.1126020676},
{"learn":[21.43787067],"iteration":965,"passed_time":3.107072627,"remaining_time":0.1093586639},
{"learn":[21.43262978],"iteration":966,"passed_time":3.109746191,"remaining_time":0.1061237066},
{"learn":[21.42116515],"iteration":967,"passed_time":3.112395218,"remaining_time":0.1028890981},
{"learn":[21.4131763],"iteration":968,"passed_time":3.114914377,"remaining_time":0.09965154352},
{"learn":[21.40920701],"iteration":969,"passed_time":3.117503983,"remaining_time":0.09641764895},
{"learn":[21.40357151],"iteration":970,"passed_time":3.120110702,"remaining_time":0.09318559256},
{"learn":[21.39713048],"iteration":971,"passed_time":3.122668444,"remaining_time":0.08995341196},
{"learn":[21.39078489],"iteration":972,"passed_time":3.125327938,"remaining_time":0.08672544123},
{"learn":[21.38765782],"iteration":973,"passed_time":3.127900487,"remaining_time":0.08349631691},
{"learn":[21.3802365],"iteration":974,"passed_time":3.130585885,"remaining_time":0.08027143294},
{"learn":[21.37318561],"iteration":975,"passed_time":3.133215073,"remaining_time":0.07704627229},
{"learn":[21.36674064],"iteration":976,"passed_time":3.135804225,"remaining_time":0.07382138914},
{"learn":[21.35937997],"iteration":977,"passed_time":3.138356414,"remaining_time":0.07059697455},
{"learn":[21.35371403],"iteration":978,"passed_time":3.141249453,"remaining_time":0.06738124465},
{"learn":[21.34781966],"iteration":979,"passed_time":3.143808473,"remaining_time":0.06415935659},
{"learn":[21.33604932],"iteration":980,"passed_time":3.146431747,"remaining_time":0.06094006441},
{"learn":[21.3278999],"iteration":981,"passed_time":3.149002858,"remaining_time":0.05772102998},
{"learn":[21.3204342],"iteration":982,"passed_time":3.151563452,"remaining_time":0.05450313193},
{"learn":[21.31579464],"iteration":983,"passed_time":3.154036994,"remaining_time":0.05128515438},
{"learn":[21.31152828],"iteration":984,"passed_time":3.156566143,"remaining_time":0.04806953517},
{"learn":[21.30737602],"iteration":985,"passed_time":3.159209946,"remaining_time":0.04485693635},
{"learn":[21.29758274],"iteration":986,"passed_time":3.161752825,"remaining_time":0.04164416081},
{"learn":[21.29166943],"iteration":987,"passed_time":3.164329841,"remaining_time":0.03843315596},
{"learn":[21.28542743],"iteration":988,"passed_time":3.167058019,"remaining_time":0.03522511447},
{"learn":[21.27821912],"iteration":989,"passed_time":3.170069859,"remaining_time":0.03202090767},
{"learn":[21.2714267],"iteration":990,"passed_time":3.172897074,"remaining_time":0.02881541238},
{"learn":[21.26522604],"iteration":991,"passed_time":3.175531902,"remaining_time":0.02560912824},
{"learn":[21.2576696],"iteration":992,"passed_time":3.178329724,"remaining_time":0.02240514407},
{"learn":[21.25302738],"iteration":993,"passed_time":3.180893854,"remaining_time":0.01920056652},
{"learn":[21.24748861],"iteration":994,"passed_time":3.183432085,"remaining_time":0.01599714616},
{"learn":[21.23885492],"iteration":995,"passed_time":3.186041372,"remaining_time":0.01279534688},
{"learn":[21.2333522],"iteration":996,"passed_time":3.188721011,"remaining_time":0.009594947878},
{"learn":[21.22910985],"iteration":997,"passed_time":3.19132653,"remaining_time":0.006395443947},
{"learn":[21.22316428],"iteration":998,"passed_time":3.193849634,"remaining_time":0.003197046681},
{"learn":[21.21750175],"iteration":999,"passed_time":3.196486344,"remaining_time":0}
]}